Workbook

Sheet Overview
A1: EcoLoop execution harness
A2: As of 15 October 2026 · Collaborative planning · No application implementation claimed
A3: Update Tasks inputs; phase progress counts leaf units and gates once.
A5: Phase | B5: Outcome | C5: Horizon | D5: Units | E5: Verified | F5: Progress | G5: In progress | H5: Dependency open | I5: Phase gate
A6: P00 | B6: Planning and scope approval | C6: Planning | D6: =COUNTIFS(Tasks!$B$6:$B$161,A6) -> 13 | E6: =COUNTIFS(Tasks!$B$6:$B$161,A6,Tasks!$H$6:$H$161,"Verified") -> 0 | F6: =IF(D6=0,"No units",E6/D6) -> 0 | G6: =COUNTIFS(Tasks!$B$6:$B$161,A6,Tasks!$F$6:$F$161,"In progress") -> 0 | H6: =COUNTIFS(Tasks!$B$6:$B$161,A6,Tasks!$H$6:$H$161,"Dependency open") -> 10 | I6: =VLOOKUP(A6&".90.01",Tasks!$A$6:$H$161,8,FALSE) -> Dependency open
A7: P01 | B7: Trusted foundation and contracts | C7: Demo | D7: =COUNTIFS(Tasks!$B$6:$B$161,A7) -> 13 | E7: =COUNTIFS(Tasks!$B$6:$B$161,A7,Tasks!$H$6:$H$161,"Verified") -> 0 | F7: =IF(D7=0,"No units",E7/D7) -> 0 | G7: =COUNTIFS(Tasks!$B$6:$B$161,A7,Tasks!$F$6:$F$161,"In progress") -> 0 | H7: =COUNTIFS(Tasks!$B$6:$B$161,A7,Tasks!$H$6:$H$161,"Dependency open") -> 13 | I7: =VLOOKUP(A7&".90.01",Tasks!$A$6:$H$161,8,FALSE) -> Dependency open
A8: P02 | B8: Deterministic baseline and synthetic household flow | C8: Demo | D8: =COUNTIFS(Tasks!$B$6:$B$161,A8) -> 13 | E8: =COUNTIFS(Tasks!$B$6:$B$161,A8,Tasks!$H$6:$H$161,"Verified") -> 0 | F8: =IF(D8=0,"No units",E8/D8) -> 0 | G8: =COUNTIFS(Tasks!$B$6:$B$161,A8,Tasks!$F$6:$F$161,"In progress") -> 0 | H8: =COUNTIFS(Tasks!$B$6:$B$161,A8,Tasks!$H$6:$H$161,"Dependency open") -> 13 | I8: =VLOOKUP(A8&".90.01",Tasks!$A$6:$H$161,8,FALSE) -> Dependency open
A9: P03 | B9: Gemini intake and single-orchestrator household journey | C9: Demo | D9: =COUNTIFS(Tasks!$B$6:$B$161,A9) -> 13 | E9: =COUNTIFS(Tasks!$B$6:$B$161,A9,Tasks!$H$6:$H$161,"Verified") -> 0 | F9: =IF(D9=0,"No units",E9/D9) -> 0 | G9: =COUNTIFS(Tasks!$B$6:$B$161,A9,Tasks!$F$6:$F$161,"In progress") -> 0 | H9: =COUNTIFS(Tasks!$B$6:$B$161,A9,Tasks!$H$6:$H$161,"Dependency open") -> 13 | I9: =VLOOKUP(A9&".90.01",Tasks!$A$6:$H$161,8,FALSE) -> Dependency open
A10: P04 | B10: Google deployment and submission readiness | C10: Demo | D10: =COUNTIFS(Tasks!$B$6:$B$161,A10) -> 13 | E10: =COUNTIFS(Tasks!$B$6:$B$161,A10,Tasks!$H$6:$H$161,"Verified") -> 0 | F10: =IF(D10=0,"No units",E10/D10) -> 0 | G10: =COUNTIFS(Tasks!$B$6:$B$161,A10,Tasks!$F$6:$F$161,"In progress") -> 0 | H10: =COUNTIFS(Tasks!$B$6:$B$161,A10,Tasks!$H$6:$H$161,"Dependency open") -> 13 | I10: =VLOOKUP(A10&".90.01",Tasks!$A$6:$H$161,8,FALSE) -> Dependency open
A11: P05 | B11: Institutional kitchen extension | C11: Expansion | D11: =COUNTIFS(Tasks!$B$6:$B$161,A11) -> 13 | E11: =COUNTIFS(Tasks!$B$6:$B$161,A11,Tasks!$H$6:$H$161,"Verified") -> 0 | F11: =IF(D11=0,"No units",E11/D11) -> 0 | G11: =COUNTIFS(Tasks!$B$6:$B$161,A11,Tasks!$F$6:$F$161,"In progress") -> 0 | H11: =COUNTIFS(Tasks!$B$6:$B$161,A11,Tasks!$H$6:$H$161,"Dependency open") -> 13 | I11: =VLOOKUP(A11&".90.01",Tasks!$A$6:$H$161,8,FALSE) -> Dependency open
A12: P06 | B12: Qualified recovery coordination | C12: Expansion | D12: =COUNTIFS(Tasks!$B$6:$B$161,A12) -> 13 | E12: =COUNTIFS(Tasks!$B$6:$B$161,A12,Tasks!$H$6:$H$161,"Verified") -> 0 | F12: =IF(D12=0,"No units",E12/D12) -> 0 | G12: =COUNTIFS(Tasks!$B$6:$B$161,A12,Tasks!$F$6:$F$161,"In progress") -> 0 | H12: =COUNTIFS(Tasks!$B$6:$B$161,A12,Tasks!$H$6:$H$161,"Dependency open") -> 13 | I12: =VLOOKUP(A12&".90.01",Tasks!$A$6:$H$161,8,FALSE) -> Dependency open
A13: P07 | B13: Organics and processor evidence | C13: Expansion | D13: =COUNTIFS(Tasks!$B$6:$B$161,A13) -> 13 | E13: =COUNTIFS(Tasks!$B$6:$B$161,A13,Tasks!$H$6:$H$161,"Verified") -> 0 | F13: =IF(D13=0,"No units",E13/D13) -> 0 | G13: =COUNTIFS(Tasks!$B$6:$B$161,A13,Tasks!$F$6:$F$161,"In progress") -> 0 | H13: =COUNTIFS(Tasks!$B$6:$B$161,A13,Tasks!$H$6:$H$161,"Dependency open") -> 13 | I13: =VLOOKUP(A13&".90.01",Tasks!$A$6:$H$161,8,FALSE) -> Dependency open
A14: P08 | B14: Permissioned pilot and operating model | C14: Pilot | D14: =COUNTIFS(Tasks!$B$6:$B$161,A14) -> 13 | E14: =COUNTIFS(Tasks!$B$6:$B$161,A14,Tasks!$H$6:$H$161,"Verified") -> 0 | F14: =IF(D14=0,"No units",E14/D14) -> 0 | G14: =COUNTIFS(Tasks!$B$6:$B$161,A14,Tasks!$F$6:$F$161,"In progress") -> 0 | H14: =COUNTIFS(Tasks!$B$6:$B$161,A14,Tasks!$H$6:$H$161,"Dependency open") -> 13 | I14: =VLOOKUP(A14&".90.01",Tasks!$A$6:$H$161,8,FALSE) -> Dependency open
A15: P09 | B15: Repair reuse and material exchange discovery | C15: Expansion | D15: =COUNTIFS(Tasks!$B$6:$B$161,A15) -> 13 | E15: =COUNTIFS(Tasks!$B$6:$B$161,A15,Tasks!$H$6:$H$161,"Verified") -> 0 | F15: =IF(D15=0,"No units",E15/D15) -> 0 | G15: =COUNTIFS(Tasks!$B$6:$B$161,A15,Tasks!$F$6:$F$161,"In progress") -> 0 | H15: =COUNTIFS(Tasks!$B$6:$B$161,A15,Tasks!$H$6:$H$161,"Dependency open") -> 13 | I15: =VLOOKUP(A15&".90.01",Tasks!$A$6:$H$161,8,FALSE) -> Dependency open
A16: P10 | B16: Energy and water modules discovery | C16: Expansion | D16: =COUNTIFS(Tasks!$B$6:$B$161,A16) -> 13 | E16: =COUNTIFS(Tasks!$B$6:$B$161,A16,Tasks!$H$6:$H$161,"Verified") -> 0 | F16: =IF(D16=0,"No units",E16/D16) -> 0 | G16: =COUNTIFS(Tasks!$B$6:$B$161,A16,Tasks!$F$6:$F$161,"In progress") -> 0 | H16: =COUNTIFS(Tasks!$B$6:$B$161,A16,Tasks!$H$6:$H$161,"Dependency open") -> 13 | I16: =VLOOKUP(A16&".90.01",Tasks!$A$6:$H$161,8,FALSE) -> Dependency open
A17: P11 | B17: Ecosystem scale and commercial reliability | C17: Scale | D17: =COUNTIFS(Tasks!$B$6:$B$161,A17) -> 13 | E17: =COUNTIFS(Tasks!$B$6:$B$161,A17,Tasks!$H$6:$H$161,"Verified") -> 0 | F17: =IF(D17=0,"No units",E17/D17) -> 0 | G17: =COUNTIFS(Tasks!$B$6:$B$161,A17,Tasks!$F$6:$F$161,"In progress") -> 0 | H17: =COUNTIFS(Tasks!$B$6:$B$161,A17,Tasks!$H$6:$H$161,"Dependency open") -> 13 | I17: =VLOOKUP(A17&".90.01",Tasks!$A$6:$H$161,8,FALSE) -> Dependency open
A20: Total planned units | B20: =COUNTA(Tasks!$A$6:$A$161) -> 156
A21: Verified units | B21: =COUNTIFS(Tasks!$H$6:$H$161,"Verified") -> 0
A22: Demo gate | B22: =VLOOKUP("P04.90.01",Tasks!$A$6:$H$161,8,FALSE) -> Dependency open
A25: Blueprint folder | B25: https://drive.google.com/drive/folders/1mhYQLzTWc1uwqF9BkkkIy44y7R6GikpC
A26: Control room link | B26: Added after document publication
A29: Formula verification cannot establish that evidence is truthful; accountable review remains required.

Sheet Tasks
A1: EcoLoop tasks — live completion and evidence
A2: Use filters; preserve row order. Checked boxes need evidence, reviewer, date and verified prerequisites.
A3: Initial state: proposed tasks only. Owner roles are placeholders; coding is not authorized by this documentation request.
A5: Unit ID | B5: Phase | C5: Parent task | D5: Granular unit | E5: Owner | F5: Status | G5: Done | H5: Calculated result | I5: Evidence link | J5: Reviewer | K5: Updated (ISO) | L5: Prerequisite 1 | M5: Prerequisite 2 | N5: Prerequisite 3 | O5: Dependency readiness | P5: Acceptance condition | Q5: Expected evidence | R5: Estimate hours | S5: Context tokens | T5: Requirement / journey | U5: Blocker / notes | V5: Horizon
A6: P00.01.01 | B6: P00 | C6: P00.01 Product and evidence | D6: Review source inventory and conflicts | E6: Product owner | F6: Not started | G6: FALSE | H6: =IF(COUNTIFS($A$6:$A$161,A6)<>1,"Duplicate ID",IF(O6<>"Ready","Dependency open",IF(G6=TRUE,IF(AND(F6="Complete",I6<>"",J6<>"",K6<>""),"Verified","Evidence required"),IF(F6="Complete","Check completion",IF(F6="Blocked","Blocked",IF(F6="In progress","In progress",IF(F6="In review","In review","Open"))))))) -> Open | O6: ="Ready" -> Ready | P6: Coverage and contradiction register acknowledged; source gaps have owners | Q6: Research inventory + product source review | S6: 6000 | T6: REQ-SCOPE-01 | U6: Proposed work; implementation not authorized by this documentation request. | V6: Planning
A7: P00.01.02 | B7: P00 | C7: P00.01 Product and evidence | D7: Select initial actor and decision window | E7: Product owner | F7: Not started | G7: FALSE | H7: =IF(COUNTIFS($A$6:$A$161,A7)<>1,"Duplicate ID",IF(O7<>"Ready","Dependency open",IF(G7=TRUE,IF(AND(F7="Complete",I7<>"",J7<>"",K7<>""),"Verified","Evidence required"),IF(F7="Complete","Check completion",IF(F7="Blocked","Blocked",IF(F7="In progress","In progress",IF(F7="In review","In review","Open"))))))) -> Dependency open | L7: P00.01.01 | O7: =IF(AND(OR(L7="",IFNA(VLOOKUP(L7,$A$6:$H$6,8,FALSE),"Missing")="Verified"),OR(M7="",IFNA(VLOOKUP(M7,$A$6:$H$6,8,FALSE),"Missing")="Verified"),OR(N7="",IFNA(VLOOKUP(N7,$A$6:$H$6,8,FALSE),"Missing")="Verified")),"Ready","Dependency open") -> Dependency open | P7: Named cook/buyer, authority and before-cooking trigger documented | Q7: Product strategy scope decision | S7: 6000 | T7: REQ-SCOPE-01 | U7: Proposed work; implementation not authorized by this documentation request. | V7: Planning
A8: P00.01.03 | B8: P00 | C8: P00.01 Product and evidence | D8: Approve one-lane demo boundary | E8: Product owner | F8: Not started | G8: FALSE | H8: =IF(COUNTIFS($A$6:$A$161,A8)<>1,"Duplicate ID",IF(O8<>"Ready","Dependency open",IF(G8=TRUE,IF(AND(F8="Complete",I8<>"",J8<>"",K8<>""),"Verified","Evidence required"),IF(F8="Complete","Check completion",IF(F8="Blocked","Blocked",IF(F8="In progress","In progress",IF(F8="In review","In review","Open"))))))) -> Dependency open | L8: P00.01.02 | O8: =IF(AND(OR(L8="",IFNA(VLOOKUP(L8,$A$6:$H$7,8,FALSE),"Missing")="Verified"),OR(M8="",IFNA(VLOOKUP(M8,$A$6:$H$7,8,FALSE),"Missing")="Verified"),OR(N8="",IFNA(VLOOKUP(N8,$A$6:$H$7,8,FALSE),"Missing")="Verified")),"Ready","Dependency open") -> Dependency open | P8: Household path chosen or alternative documented; other lanes staged | Q8: Signed scope decision DEC-PLAT-001 | S8: 6000 | T8: REQ-SCOPE-01 | U8: Proposed work; implementation not authorized by this documentation request. | V8: Planning
A9: P00.01.04 | B9: P00 | C9: P00.01 Product and evidence | D9: Define success and stop conditions | E9: Product owner | F9: Not started | G9: FALSE | H9: =IF(COUNTIFS($A$6:$A$161,A9)<>1,"Duplicate ID",IF(O9<>"Ready","Dependency open",IF(G9=TRUE,IF(AND(F9="Complete",I9<>"",J9<>"",K9<>""),"Verified","Evidence required"),IF(F9="Complete","Check completion",IF(F9="Blocked","Blocked",IF(F9="In progress","In progress",IF(F9="In review","In review","Open"))))))) -> Dependency open | L9: P00.01.03 | O9: =IF(AND(OR(L9="",IFNA(VLOOKUP(L9,$A$6:$H$8,8,FALSE),"Missing")="Verified"),OR(M9="",IFNA(VLOOKUP(M9,$A$6:$H$8,8,FALSE),"Missing")="Verified"),OR(N9="",IFNA(VLOOKUP(N9,$A$6:$H$8,8,FALSE),"Missing")="Verified")),"Ready","Dependency open") -> Dependency open | P9: Decision correctness, effort and zero unsafe actions defined before trial | Q9: Pilot/benchmark acceptance record | S9: 6000 | T9: REQ-SCOPE-01 | U9: Proposed work; implementation not authorized by this documentation request. | V9: Planning
A10: P00.02.01 | B10: P00 | C10: P00.02 Constraints and access | D10: Verify contest eligibility and deadline | E10: Technical lead | F10: Not started | G10: FALSE | H10: =IF(COUNTIFS($A$6:$A$161,A10)<>1,"Duplicate ID",IF(O10<>"Ready","Dependency open",IF(G10=TRUE,IF(AND(F10="Complete",I10<>"",J10<>"",K10<>""),"Verified","Evidence required"),IF(F10="Complete","Check completion",IF(F10="Blocked","Blocked",IF(F10="In progress","In progress",IF(F10="In review","In review","Open"))))))) -> Open | O10: =IF(AND(OR(L10="",IFNA(VLOOKUP(L10,$A$6:$H$9,8,FALSE),"Missing")="Verified"),OR(M10="",IFNA(VLOOKUP(M10,$A$6:$H$9,8,FALSE),"Missing")="Verified"),OR(N10="",IFNA(VLOOKUP(N10,$A$6:$H$9,8,FALSE),"Missing")="Verified")),"Ready","Dependency open") -> Ready | P10: Official terms, roster status and exact cutoff uncertainty recorded | Q10: Official source URLs and eligibility note | S10: 6000 | T10: REQ-SCOPE-01 | U10: Proposed work; implementation not authorized by this documentation request. | V10: Planning
A11: P00.02.02 | B11: P00 | C11: P00.02 Constraints and access | D11: Inventory cloud and model access | E11: Technical lead | F11: Not started | G11: FALSE | H11: =IF(COUNTIFS($A$6:$A$161,A11)<>1,"Duplicate ID",IF(O11<>"Ready","Dependency open",IF(G11=TRUE,IF(AND(F11="Complete",I11<>"",J11<>"",K11<>""),"Verified","Evidence required"),IF(F11="Complete","Check completion",IF(F11="Blocked","Blocked",IF(F11="In progress","In progress",IF(F11="In review","In review","Open"))))))) -> Dependency open | L11: P00.02.01 | O11: =IF(AND(OR(L11="",IFNA(VLOOKUP(L11,$A$6:$H$10,8,FALSE),"Missing")="Verified"),OR(M11="",IFNA(VLOOKUP(M11,$A$6:$H$10,8,FALSE),"Missing")="Verified"),OR(N11="",IFNA(VLOOKUP(N11,$A$6:$H$10,8,FALSE),"Missing")="Verified")),"Ready","Dependency open") -> Dependency open | P11: IAM, billing, region, quota and supported runtime verified without exposing secrets | Q11: Redacted access checklist | S11: 6000 | T11: REQ-SCOPE-01 | U11: Proposed work; implementation not authorized by this documentation request. | V11: Planning
A12: P00.02.03 | B12: P00 | C12: P00.02 Constraints and access | D12: Review food policy and measurement assumptions | E12: Technical lead | F12: Not started | G12: FALSE | H12: =IF(COUNTIFS($A$6:$A$161,A12)<>1,"Duplicate ID",IF(O12<>"Ready","Dependency open",IF(G12=TRUE,IF(AND(F12="Complete",I12<>"",J12<>"",K12<>""),"Verified","Evidence required"),IF(F12="Complete","Check completion",IF(F12="Blocked","Blocked",IF(F12="In progress","In progress",IF(F12="In review","In review","Open"))))))) -> Dependency open | L12: P00.02.02 | O12: =IF(AND(OR(L12="",IFNA(VLOOKUP(L12,$A$6:$H$11,8,FALSE),"Missing")="Verified"),OR(M12="",IFNA(VLOOKUP(M12,$A$6:$H$11,8,FALSE),"Missing")="Verified"),OR(N12="",IFNA(VLOOKUP(N12,$A$6:$H$11,8,FALSE),"Missing")="Verified")),"Ready","Dependency open") -> Dependency open | P12: Unsupported universal thresholds/cutoffs rejected; reviewer named | Q12: Policy discrepancy register | S12: 6000 | T12: REQ-SCOPE-01 | U12: Proposed work; implementation not authorized by this documentation request. | V12: Planning
A13: P00.02.04 | B13: P00 | C13: P00.02 Constraints and access | D13: Approve privacy and partner boundaries | E13: Technical lead | F13: Not started | G13: FALSE | H13: =IF(COUNTIFS($A$6:$A$161,A13)<>1,"Duplicate ID",IF(O13<>"Ready","Dependency open",IF(G13=TRUE,IF(AND(F13="Complete",I13<>"",J13<>"",K13<>""),"Verified","Evidence required"),IF(F13="Complete","Check completion",IF(F13="Blocked","Blocked",IF(F13="In progress","In progress",IF(F13="In review","In review","Open"))))))) -> Dependency open | L13: P00.02.03 | O13: =IF(AND(OR(L13="",IFNA(VLOOKUP(L13,$A$6:$H$12,8,FALSE),"Missing")="Verified"),OR(M13="",IFNA(VLOOKUP(M13,$A$6:$H$12,8,FALSE),"Missing")="Verified"),OR(N13="",IFNA(VLOOKUP(N13,$A$6:$H$12,8,FALSE),"Missing")="Verified")),"Ready","Dependency open") -> Dependency open | P13: Consent, public-repo data exclusion and simulated-only adapters specified | Q13: Privacy/partner decision record | S13: 6000 | T13: REQ-SCOPE-01 | U13: Proposed work; implementation not authorized by this documentation request. | V13: Planning
A14: P00.03.01 | B14: P00 | C14: P00.03 Execution setup | D14: Review HLD and LLD against scope | E14: Technical lead | F14: Not started | G14: FALSE | H14: =IF(COUNTIFS($A$6:$A$161,A14)<>1,"Duplicate ID",IF(O14<>"Ready","Dependency open",IF(G14=TRUE,IF(AND(F14="Complete",I14<>"",J14<>"",K14<>""),"Verified","Evidence required"),IF(F14="Complete","Check completion",IF(F14="Blocked","Blocked",IF(F14="In progress","In progress",IF(F14="In review","In review","Open"))))))) -> Open | O14: =IF(AND(OR(L14="",IFNA(VLOOKUP(L14,$A$6:$H$13,8,FALSE),"Missing")="Verified"),OR(M14="",IFNA(VLOOKUP(M14,$A$6:$H$13,8,FALSE),"Missing")="Verified"),OR(N14="",IFNA(VLOOKUP(N14,$A$6:$H$13,8,FALSE),"Missing")="Verified")),"Ready","Dependency open") -> Ready | P14: Auth, versions, approvals, idempotency and failure contracts agreed | Q14: Technical design review | S14: 6000 | T14: REQ-SCOPE-01 | U14: Proposed work; implementation not authorized by this documentation request. | V14: Planning
A15: P00.03.02 | B15: P00 | C15: P00.03 Execution setup | D15: Assign owners and estimates | E15: Technical lead | F15: Not started | G15: FALSE | H15: =IF(COUNTIFS($A$6:$A$161,A15)<>1,"Duplicate ID",IF(O15<>"Ready","Dependency open",IF(G15=TRUE,IF(AND(F15="Complete",I15<>"",J15<>"",K15<>""),"Verified","Evidence required"),IF(F15="Complete","Check completion",IF(F15="Blocked","Blocked",IF(F15="In progress","In progress",IF(F15="In review","In review","Open"))))))) -> Dependency open | L15: P00.03.01 | O15: =IF(AND(OR(L15="",IFNA(VLOOKUP(L15,$A$6:$H$14,8,FALSE),"Missing")="Verified"),OR(M15="",IFNA(VLOOKUP(M15,$A$6:$H$14,8,FALSE),"Missing")="Verified"),OR(N15="",IFNA(VLOOKUP(N15,$A$6:$H$14,8,FALSE),"Missing")="Verified")),"Ready","Dependency open") -> Dependency open | P15: Named owner, reviewer and effort for first executable work packet | Q15: Updated tracker rows | S15: 6000 | T15: REQ-SCOPE-01 | U15: Proposed work; implementation not authorized by this documentation request. | V15: Planning
A16: P00.03.03 | B16: P00 | C16: P00.03 Execution setup | D16: Exercise harness status and recovery | E16: Technical lead | F16: Not started | G16: FALSE | H16: =IF(COUNTIFS($A$6:$A$161,A16)<>1,"Duplicate ID",IF(O16<>"Ready","Dependency open",IF(G16=TRUE,IF(AND(F16="Complete",I16<>"",J16<>"",K16<>""),"Verified","Evidence required"),IF(F16="Complete","Check completion",IF(F16="Blocked","Blocked",IF(F16="In progress","In progress",IF(F16="In review","In review","Open"))))))) -> Dependency open | L16: P00.03.02 | O16: =IF(AND(OR(L16="",IFNA(VLOOKUP(L16,$A$6:$H$15,8,FALSE),"Missing")="Verified"),OR(M16="",IFNA(VLOOKUP(M16,$A$6:$H$15,8,FALSE),"Missing")="Verified"),OR(N16="",IFNA(VLOOKUP(N16,$A$6:$H$15,8,FALSE),"Missing")="Verified")),"Ready","Dependency open") -> Dependency open | P16: Checkbox alone cannot verify; dependencies and evidence gates recalculate | Q16: Harness verification record | S16: 6000 | T16: REQ-SCOPE-01 | U16: Proposed work; implementation not authorized by this documentation request. | V16: Planning
A17: P00.03.04 | B17: P00 | C17: P00.03 Execution setup | D17: Authorize implementation phase | E17: Technical lead | F17: Not started | G17: FALSE | H17: =IF(COUNTIFS($A$6:$A$161,A17)<>1,"Duplicate ID",IF(O17<>"Ready","Dependency open",IF(G17=TRUE,IF(AND(F17="Complete",I17<>"",J17<>"",K17<>""),"Verified","Evidence required"),IF(F17="Complete","Check completion",IF(F17="Blocked","Blocked",IF(F17="In progress","In progress",IF(F17="In review","In review","Open"))))))) -> Dependency open | L17: P00.03.03 | O17: =IF(AND(OR(L17="",IFNA(VLOOKUP(L17,$A$6:$H$16,8,FALSE),"Missing")="Verified"),OR(M17="",IFNA(VLOOKUP(M17,$A$6:$H$16,8,FALSE),"Missing")="Verified"),OR(N17="",IFNA(VLOOKUP(N17,$A$6:$H$16,8,FALSE),"Missing")="Verified")),"Ready","Dependency open") -> Dependency open | P17: Human authorizes coding scope; document-only restriction explicitly lifted | Q17: Authorization record | S17: 6000 | T17: REQ-SCOPE-01 | U17: Proposed work; implementation not authorized by this documentation request. | V17: Planning
A18: P00.90.01 | B18: P00 | C18: P00.90 Phase gate | D18: Review and accept planning and scope approval | E18: Product owner + independent reviewer | F18: Not started | G18: FALSE | H18: =IF(COUNTIFS($A$6:$A$161,A18)<>1,"Duplicate ID",IF(O18<>"Ready","Dependency open",IF(G18=TRUE,IF(AND(F18="Complete",I18<>"",J18<>"",K18<>""),"Verified","Evidence required"),IF(F18="Complete","Check completion",IF(F18="Blocked","Blocked",IF(F18="In progress","In progress",IF(F18="In review","In review","Open"))))))) -> Dependency open | L18: P00.01.04 | M18: P00.02.04 | N18: P00.03.04 | O18: =IF(AND(OR(L18="",IFNA(VLOOKUP(L18,$A$6:$H$17,8,FALSE),"Missing")="Verified"),OR(M18="",IFNA(VLOOKUP(M18,$A$6:$H$17,8,FALSE),"Missing")="Verified"),OR(N18="",IFNA(VLOOKUP(N18,$A$6:$H$17,8,FALSE),"Missing")="Verified")),"Ready","Dependency open") -> Dependency open | P18: All prerequisites verified; critical risks closed or explicitly rejected for rollout; human records go/revise/stop decision. | Q18: Phase gate record with reviewer, evidence links, residual risks and next scope | S18: 4000 | T18: P00-GATE | U18: Unchecked until phase evidence is reviewed. A written plan is not implementation evidence. | V18: Planning
A19: P01.01.01 | B19: P01 | C19: P01.01 Identity and permissions | D19: Define membership and permission matrix | E19: Backend engineer | F19: Not started | G19: FALSE | H19: =IF(COUNTIFS($A$6:$A$161,A19)<>1,"Duplicate ID",IF(O19<>"Ready","Dependency open",IF(G19=TRUE,IF(AND(F19="Complete",I19<>"",J19<>"",K19<>""),"Verified","Evidence required"),IF(F19="Complete","Check completion",IF(F19="Blocked","Blocked",IF(F19="In progress","In progress",IF(F19="In review","In review","Open"))))))) -> Dependency open | L19: P00.90.01 | O19: =IF(AND(OR(L19="",IFNA(VLOOKUP(L19,$A$6:$H$18,8,FALSE),"Missing")="Verified"),OR(M19="",IFNA(VLOOKUP(M19,$A$6:$H$18,8,FALSE),"Missing")="Verified"),OR(N19="",IFNA(VLOOKUP(N19,$A$6:$H$18,8,FALSE),"Missing")="Verified")),"Ready","Dependency open") -> Dependency open | P19: Each protected operation maps actor, tenant and permission | Q19: Auth contract REQ-AUTH-01 | S19: 6000 | T19: REQ-AUTH-01 / REQ-FACT-01 | U19: Proposed work; implementation not authorized by this documentation request. | V19: Demo
A20: P01.01.02 | B20: P01 | C20: P01.01 Identity and permissions | D20: Implement verified identity boundary | E20: Backend engineer | F20: Not started | G20: FALSE | H20: =IF(COUNTIFS($A$6:$A$161,A20)<>1,"Duplicate ID",IF(O20<>"Ready","Dependency open",IF(G20=TRUE,IF(AND(F20="Complete",I20<>"",J20<>"",K20<>""),"Verified","Evidence required"),IF(F20="Complete","Check completion",IF(F20="Blocked","Blocked",IF(F20="In progress","In progress",IF(F20="In review","In review","Open"))))))) -> Dependency open | L20: P01.01.01 | O20: =IF(AND(OR(L20="",IFNA(VLOOKUP(L20,$A$6:$H$19,8,FALSE),"Missing")="Verified"),OR(M20="",IFNA(VLOOKUP(M20,$A$6:$H$19,8,FALSE),"Missing")="Verified"),OR(N20="",IFNA(VLOOKUP(N20,$A$6:$H$19,8,FALSE),"Missing")="Verified")),"Ready","Dependency open") -> Dependency open | P20: Missing/invalid token rejected; tenant never defaults | Q20: Auth check evidence | S20: 6000 | T20: REQ-AUTH-01 / REQ-FACT-01 | U20: Proposed work; implementation not authorized by this documentation request. | V20: Demo
A21: P01.01.03 | B21: P01 | C21: P01.01 Identity and permissions | D21: Implement current membership and revocation checks | E21: Backend engineer | F21: Not started | G21: FALSE | H21: =IF(COUNTIFS($A$6:$A$161,A21)<>1,"Duplicate ID",IF(O21<>"Ready","Dependency open",IF(G21=TRUE,IF(AND(F21="Complete",I21<>"",J21<>"",K21<>""),"Verified","Evidence required"),IF(F21="Complete","Check completion",IF(F21="Blocked","Blocked",IF(F21="In progress","In progress",IF(F21="In review","In review","Open"))))))) -> Dependency open | L21: P01.01.02 | O21: =IF(AND(OR(L21="",IFNA(VLOOKUP(L21,$A$6:$H$20,8,FALSE),"Missing")="Verified"),OR(M21="",IFNA(VLOOKUP(M21,$A$6:$H$20,8,FALSE),"Missing")="Verified"),OR(N21="",IFNA(VLOOKUP(N21,$A$6:$H$20,8,FALSE),"Missing")="Verified")),"Ready","Dependency open") -> Dependency open | P21: Revoked membership fails even with a still-valid token | Q21: Revocation and wrong-tenant evidence | S21: 6000 | T21: REQ-AUTH-01 / REQ-FACT-01 | U21: Proposed work; implementation not authorized by this documentation request. | V21: Demo
A22: P01.01.04 | B22: P01 | C22: P01.01 Identity and permissions | D22: Prove denial across roles and tenants | E22: Backend engineer | F22: Not started | G22: FALSE | H22: =IF(COUNTIFS($A$6:$A$161,A22)<>1,"Duplicate ID",IF(O22<>"Ready","Dependency open",IF(G22=TRUE,IF(AND(F22="Complete",I22<>"",J22<>"",K22<>""),"Verified","Evidence required"),IF(F22="Complete","Check completion",IF(F22="Blocked","Blocked",IF(F22="In progress","In progress",IF(F22="In review","In review","Open"))))))) -> Dependency open | L22: P01.01.03 | O22: =IF(AND(OR(L22="",IFNA(VLOOKUP(L22,$A$6:$H$21,8,FALSE),"Missing")="Verified"),OR(M22="",IFNA(VLOOKUP(M22,$A$6:$H$21,8,FALSE),"Missing")="Verified"),OR(N22="",IFNA(VLOOKUP(N22,$A$6:$H$21,8,FALSE),"Missing")="Verified")),"Ready","Dependency open") -> Dependency open | P22: Read/write isolation and guessed IDs tested | Q22: Negative authorization matrix | S22: 6000 | T22: REQ-AUTH-01 / REQ-FACT-01 | U22: Proposed work; implementation not authorized by this documentation request. | V22: Demo
A23: P01.02.01 | B23: P01 | C23: P01.02 Canonical records | D23: Define typed records and units | E23: Backend engineer | F23: Not started | G23: FALSE | H23: =IF(COUNTIFS($A$6:$A$161,A23)<>1,"Duplicate ID",IF(O23<>"Ready","Dependency open",IF(G23=TRUE,IF(AND(F23="Complete",I23<>"",J23<>"",K23<>""),"Verified","Evidence required"),IF(F23="Complete","Check completion",IF(F23="Blocked","Blocked",IF(F23="In progress","In progress",IF(F23="In review","In review","Open"))))))) -> Dependency open | L23: P00.90.01 | O23: =IF(AND(OR(L23="",IFNA(VLOOKUP(L23,$A$6:$H$22,8,FALSE),"Missing")="Verified"),OR(M23="",IFNA(VLOOKUP(M23,$A$6:$H$22,8,FALSE),"Missing")="Verified"),OR(N23="",IFNA(VLOOKUP(N23,$A$6:$H$22,8,FALSE),"Missing")="Verified")),"Ready","Dependency open") -> Dependency open | P23: Candidate, fact, proposal, evidence, outcome schemas include version and provenance | Q23: Schema review | S23: 6000 | T23: REQ-AUTH-01 / REQ-FACT-01 | U23: Proposed work; implementation not authorized by this documentation request. | V23: Demo
A24: P01.02.02 | B24: P01 | C24: P01.02 Canonical records | D24: Define tenant paths and server-only writes | E24: Backend engineer | F24: Not started | G24: FALSE | H24: =IF(COUNTIFS($A$6:$A$161,A24)<>1,"Duplicate ID",IF(O24<>"Ready","Dependency open",IF(G24=TRUE,IF(AND(F24="Complete",I24<>"",J24<>"",K24<>""),"Verified","Evidence required"),IF(F24="Complete","Check completion",IF(F24="Blocked","Blocked",IF(F24="In progress","In progress",IF(F24="In review","In review","Open"))))))) -> Dependency open | L24: P01.02.01 | O24: =IF(AND(OR(L24="",IFNA(VLOOKUP(L24,$A$6:$H$23,8,FALSE),"Missing")="Verified"),OR(M24="",IFNA(VLOOKUP(M24,$A$6:$H$23,8,FALSE),"Missing")="Verified"),OR(N24="",IFNA(VLOOKUP(N24,$A$6:$H$23,8,FALSE),"Missing")="Verified")),"Ready","Dependency open") -> Dependency open | P24: No global list or browser mutation bypass; server IAM assessed | Q24: Firestore access design | S24: 6000 | T24: REQ-AUTH-01 / REQ-FACT-01 | U24: Proposed work; implementation not authorized by this documentation request. | V24: Demo
A25: P01.02.03 | B25: P01 | C25: P01.02 Canonical records | D25: Implement atomic versioned confirmation | E25: Backend engineer | F25: Not started | G25: FALSE | H25: =IF(COUNTIFS($A$6:$A$161,A25)<>1,"Duplicate ID",IF(O25<>"Ready","Dependency open",IF(G25=TRUE,IF(AND(F25="Complete",I25<>"",J25<>"",K25<>""),"Verified","Evidence required"),IF(F25="Complete","Check completion",IF(F25="Blocked","Blocked",IF(F25="In progress","In progress",IF(F25="In review","In review","Open"))))))) -> Dependency open | L25: P01.02.02 | O25: =IF(AND(OR(L25="",IFNA(VLOOKUP(L25,$A$6:$H$24,8,FALSE),"Missing")="Verified"),OR(M25="",IFNA(VLOOKUP(M25,$A$6:$H$24,8,FALSE),"Missing")="Verified"),OR(N25="",IFNA(VLOOKUP(N25,$A$6:$H$24,8,FALSE),"Missing")="Verified")),"Ready","Dependency open") -> Dependency open | P25: Stale version causes conflict; repeat submission does not duplicate facts | Q25: Confirmation conflict evidence | S25: 6000 | T25: REQ-AUTH-01 / REQ-FACT-01 | U25: Proposed work; implementation not authorized by this documentation request. | V25: Demo
A26: P01.02.04 | B26: P01 | C26: P01.02 Canonical records | D26: Prove durable audit and restart behavior | E26: Backend engineer | F26: Not started | G26: FALSE | H26: =IF(COUNTIFS($A$6:$A$161,A26)<>1,"Duplicate ID",IF(O26<>"Ready","Dependency open",IF(G26=TRUE,IF(AND(F26="Complete",I26<>"",J26<>"",K26<>""),"Verified","Evidence required"),IF(F26="Complete","Check completion",IF(F26="Blocked","Blocked",IF(F26="In progress","In progress",IF(F26="In review","In review","Open"))))))) -> Dependency open | L26: P01.02.03 | O26: =IF(AND(OR(L26="",IFNA(VLOOKUP(L26,$A$6:$H$25,8,FALSE),"Missing")="Verified"),OR(M26="",IFNA(VLOOKUP(M26,$A$6:$H$25,8,FALSE),"Missing")="Verified"),OR(N26="",IFNA(VLOOKUP(N26,$A$6:$H$25,8,FALSE),"Missing")="Verified")),"Ready","Dependency open") -> Dependency open | P26: Business state survives restart; sensitive content excluded from logs | Q26: Persistence and redaction evidence | S26: 6000 | T26: REQ-AUTH-01 / REQ-FACT-01 | U26: Proposed work; implementation not authorized by this documentation request. | V26: Demo
A27: P01.03.01 | B27: P01 | C27: P01.03 Runtime foundation | D27: Confirm supported frontend and Node pairing | E27: Platform engineer | F27: Not started | G27: FALSE | H27: =IF(COUNTIFS($A$6:$A$161,A27)<>1,"Duplicate ID",IF(O27<>"Ready","Dependency open",IF(G27=TRUE,IF(AND(F27="Complete",I27<>"",J27<>"",K27<>""),"Verified","Evidence required"),IF(F27="Complete","Check completion",IF(F27="Blocked","Blocked",IF(F27="In progress","In progress",IF(F27="In review","In review","Open"))))))) -> Dependency open | L27: P00.90.01 | O27: =IF(AND(OR(L27="",IFNA(VLOOKUP(L27,$A$6:$H$26,8,FALSE),"Missing")="Verified"),OR(M27="",IFNA(VLOOKUP(M27,$A$6:$H$26,8,FALSE),"Missing")="Verified"),OR(N27="",IFNA(VLOOKUP(N27,$A$6:$H$26,8,FALSE),"Missing")="Verified")),"Ready","Dependency open") -> Dependency open | P27: App Hosting compatibility verified for actual pinned versions | Q27: Runtime matrix | S27: 6000 | T27: REQ-AUTH-01 / REQ-FACT-01 | U27: Proposed work; implementation not authorized by this documentation request. | V27: Demo
A28: P01.03.02 | B28: P01 | C28: P01.03 Runtime foundation | D28: Configure authenticated API client and origins | E28: Platform engineer | F28: Not started | G28: FALSE | H28: =IF(COUNTIFS($A$6:$A$161,A28)<>1,"Duplicate ID",IF(O28<>"Ready","Dependency open",IF(G28=TRUE,IF(AND(F28="Complete",I28<>"",J28<>"",K28<>""),"Verified","Evidence required"),IF(F28="Complete","Check completion",IF(F28="Blocked","Blocked",IF(F28="In progress","In progress",IF(F28="In review","In review","Open"))))))) -> Dependency open | L28: P01.03.01 | O28: =IF(AND(OR(L28="",IFNA(VLOOKUP(L28,$A$6:$H$27,8,FALSE),"Missing")="Verified"),OR(M28="",IFNA(VLOOKUP(M28,$A$6:$H$27,8,FALSE),"Missing")="Verified"),OR(N28="",IFNA(VLOOKUP(N28,$A$6:$H$27,8,FALSE),"Missing")="Verified")),"Ready","Dependency open") -> Dependency open | P28: Environment URL used; production origins explicit; localhost not shipped | Q28: Client/CORS evidence | S28: 6000 | T28: REQ-AUTH-01 / REQ-FACT-01 | U28: Proposed work; implementation not authorized by this documentation request. | V28: Demo
A29: P01.03.03 | B29: P01 | C29: P01.03 Runtime foundation | D29: Create health and deployment contract | E29: Platform engineer | F29: Not started | G29: FALSE | H29: =IF(COUNTIFS($A$6:$A$161,A29)<>1,"Duplicate ID",IF(O29<>"Ready","Dependency open",IF(G29=TRUE,IF(AND(F29="Complete",I29<>"",J29<>"",K29<>""),"Verified","Evidence required"),IF(F29="Complete","Check completion",IF(F29="Blocked","Blocked",IF(F29="In progress","In progress",IF(F29="In review","In review","Open"))))))) -> Dependency open | L29: P01.03.02 | O29: =IF(AND(OR(L29="",IFNA(VLOOKUP(L29,$A$6:$H$28,8,FALSE),"Missing")="Verified"),OR(M29="",IFNA(VLOOKUP(M29,$A$6:$H$28,8,FALSE),"Missing")="Verified"),OR(N29="",IFNA(VLOOKUP(N29,$A$6:$H$28,8,FALSE),"Missing")="Verified")),"Ready","Dependency open") -> Dependency open | P29: Root health path stable; PORT and startup behavior documented | Q29: Health/deployment smoke evidence | S29: 6000 | T29: REQ-AUTH-01 / REQ-FACT-01 | U29: Proposed work; implementation not authorized by this documentation request. | V29: Demo
A30: P01.03.04 | B30: P01 | C30: P01.03 Runtime foundation | D30: Set budgets and model call caps | E30: Platform engineer | F30: Not started | G30: FALSE | H30: =IF(COUNTIFS($A$6:$A$161,A30)<>1,"Duplicate ID",IF(O30<>"Ready","Dependency open",IF(G30=TRUE,IF(AND(F30="Complete",I30<>"",J30<>"",K30<>""),"Verified","Evidence required"),IF(F30="Complete","Check completion",IF(F30="Blocked","Blocked",IF(F30="In progress","In progress",IF(F30="In review","In review","Open"))))))) -> Dependency open | L30: P01.03.03 | O30: =IF(AND(OR(L30="",IFNA(VLOOKUP(L30,$A$6:$H$29,8,FALSE),"Missing")="Verified"),OR(M30="",IFNA(VLOOKUP(M30,$A$6:$H$29,8,FALSE),"Missing")="Verified"),OR(N30="",IFNA(VLOOKUP(N30,$A$6:$H$29,8,FALSE),"Missing")="Verified")),"Ready","Dependency open") -> Dependency open | P30: Quota, maximum attempts/tokens and alerts have owners | Q30: Budget configuration evidence | S30: 6000 | T30: REQ-AUTH-01 / REQ-FACT-01 | U30: Proposed work; implementation not authorized by this documentation request. | V30: Demo
A31: P01.90.01 | B31: P01 | C31: P01.90 Phase gate | D31: Review and accept trusted foundation and contracts | E31: Product owner + independent reviewer | F31: Not started | G31: FALSE | H31: =IF(COUNTIFS($A$6:$A$161,A31)<>1,"Duplicate ID",IF(O31<>"Ready","Dependency open",IF(G31=TRUE,IF(AND(F31="Complete",I31<>"",J31<>"",K31<>""),"Verified","Evidence required"),IF(F31="Complete","Check completion",IF(F31="Blocked","Blocked",IF(F31="In progress","In progress",IF(F31="In review","In review","Open"))))))) -> Dependency open | L31: P01.01.04 | M31: P01.02.04 | N31: P01.03.04 | O31: =IF(AND(OR(L31="",IFNA(VLOOKUP(L31,$A$6:$H$30,8,FALSE),"Missing")="Verified"),OR(M31="",IFNA(VLOOKUP(M31,$A$6:$H$30,8,FALSE),"Missing")="Verified"),OR(N31="",IFNA(VLOOKUP(N31,$A$6:$H$30,8,FALSE),"Missing")="Verified")),"Ready","Dependency open") -> Dependency open | P31: All prerequisites verified; critical risks closed or explicitly rejected for rollout; human records go/revise/stop decision. | Q31: Phase gate record with reviewer, evidence links, residual risks and next scope | S31: 4000 | T31: P01-GATE | U31: Unchecked until phase evidence is reviewed. A written plan is not implementation evidence. | V31: Demo
A32: P02.01.01 | B32: P02 | C32: P02.01 Decision rules | D32: Specify pantry and meal change fixtures | E32: Backend engineer | F32: Not started | G32: FALSE | H32: =IF(COUNTIFS($A$6:$A$161,A32)<>1,"Duplicate ID",IF(O32<>"Ready","Dependency open",IF(G32=TRUE,IF(AND(F32="Complete",I32<>"",J32<>"",K32<>""),"Verified","Evidence required"),IF(F32="Complete","Check completion",IF(F32="Blocked","Blocked",IF(F32="In progress","In progress",IF(F32="In review","In review","Open"))))))) -> Dependency open | L32: P01.90.01 | O32: =IF(AND(OR(L32="",IFNA(VLOOKUP(L32,$A$6:$H$31,8,FALSE),"Missing")="Verified"),OR(M32="",IFNA(VLOOKUP(M32,$A$6:$H$31,8,FALSE),"Missing")="Verified"),OR(N32="",IFNA(VLOOKUP(N32,$A$6:$H$31,8,FALSE),"Missing")="Verified")),"Ready","Dependency open") -> Dependency open | P32: Stock freshness, ownership, units and consumed quantities explicit | Q32: Fixture definitions | S32: 6000 | T32: J-H01 / REQ-ACT-01 | U32: Proposed work; implementation not authorized by this documentation request. | V32: Demo
A33: P02.01.02 | B33: P02 | C33: P02.01 Decision rules | D33: Implement unit-safe quantity reconciliation | E33: Backend engineer | F33: Not started | G33: FALSE | H33: =IF(COUNTIFS($A$6:$A$161,A33)<>1,"Duplicate ID",IF(O33<>"Ready","Dependency open",IF(G33=TRUE,IF(AND(F33="Complete",I33<>"",J33<>"",K33<>""),"Verified","Evidence required"),IF(F33="Complete","Check completion",IF(F33="Blocked","Blocked",IF(F33="In progress","In progress",IF(F33="In review","In review","Open"))))))) -> Dependency open | L33: P02.01.01 | O33: =IF(AND(OR(L33="",IFNA(VLOOKUP(L33,$A$6:$H$32,8,FALSE),"Missing")="Verified"),OR(M33="",IFNA(VLOOKUP(M33,$A$6:$H$32,8,FALSE),"Missing")="Verified"),OR(N33="",IFNA(VLOOKUP(N33,$A$6:$H$32,8,FALSE),"Missing")="Verified")),"Ready","Dependency open") -> Dependency open | P33: No g/ml conversion without verified factor; no negative stock | Q33: Boundary-case outputs | S33: 6000 | T33: J-H01 / REQ-ACT-01 | U33: Proposed work; implementation not authorized by this documentation request. | V33: Demo
A34: P02.01.03 | B34: P02 | C34: P02.01 Decision rules | D34: Implement portion and cutoff rules | E34: Backend engineer | F34: Not started | G34: FALSE | H34: =IF(COUNTIFS($A$6:$A$161,A34)<>1,"Duplicate ID",IF(O34<>"Ready","Dependency open",IF(G34=TRUE,IF(AND(F34="Complete",I34<>"",J34<>"",K34<>""),"Verified","Evidence required"),IF(F34="Complete","Check completion",IF(F34="Blocked","Blocked",IF(F34="In progress","In progress",IF(F34="In review","In review","Open"))))))) -> Dependency open | L34: P02.01.02 | O34: =IF(AND(OR(L34="",IFNA(VLOOKUP(L34,$A$6:$H$33,8,FALSE),"Missing")="Verified"),OR(M34="",IFNA(VLOOKUP(M34,$A$6:$H$33,8,FALSE),"Missing")="Verified"),OR(N34="",IFNA(VLOOKUP(N34,$A$6:$H$33,8,FALSE),"Missing")="Verified")),"Ready","Dependency open") -> Dependency open | P34: Zero diners and after-cutoff behavior deterministic and explained | Q34: Rule-case outputs | S34: 6000 | T34: J-H01 / REQ-ACT-01 | U34: Proposed work; implementation not authorized by this documentation request. | V34: Demo
A35: P02.01.04 | B35: P02 | C35: P02.01 Decision rules | D35: Implement immutable simulated proposal | E35: Backend engineer | F35: Not started | G35: FALSE | H35: =IF(COUNTIFS($A$6:$A$161,A35)<>1,"Duplicate ID",IF(O35<>"Ready","Dependency open",IF(G35=TRUE,IF(AND(F35="Complete",I35<>"",J35<>"",K35<>""),"Verified","Evidence required"),IF(F35="Complete","Check completion",IF(F35="Blocked","Blocked",IF(F35="In progress","In progress",IF(F35="In review","In review","Open"))))))) -> Dependency open | L35: P02.01.03 | O35: =IF(AND(OR(L35="",IFNA(VLOOKUP(L35,$A$6:$H$34,8,FALSE),"Missing")="Verified"),OR(M35="",IFNA(VLOOKUP(M35,$A$6:$H$34,8,FALSE),"Missing")="Verified"),OR(N35="",IFNA(VLOOKUP(N35,$A$6:$H$34,8,FALSE),"Missing")="Verified")),"Ready","Dependency open") -> Dependency open | P35: Snapshot versions, expiry and preview hash stored; simulated true | Q35: Proposal contract evidence | S35: 6000 | T35: J-H01 / REQ-ACT-01 | U35: Proposed work; implementation not authorized by this documentation request. | V35: Demo
A36: P02.02.01 | B36: P02 | C36: P02.02 Evaluation baseline | D36: Annotate household gold cases | E36: Evaluation reviewer | F36: Not started | G36: FALSE | H36: =IF(COUNTIFS($A$6:$A$161,A36)<>1,"Duplicate ID",IF(O36<>"Ready","Dependency open",IF(G36=TRUE,IF(AND(F36="Complete",I36<>"",J36<>"",K36<>""),"Verified","Evidence required"),IF(F36="Complete","Check completion",IF(F36="Blocked","Blocked",IF(F36="In progress","In progress",IF(F36="In review","In review","Open"))))))) -> Dependency open | L36: P01.90.01 | O36: =IF(AND(OR(L36="",IFNA(VLOOKUP(L36,$A$6:$H$35,8,FALSE),"Missing")="Verified"),OR(M36="",IFNA(VLOOKUP(M36,$A$6:$H$35,8,FALSE),"Missing")="Verified"),OR(N36="",IFNA(VLOOKUP(N36,$A$6:$H$35,8,FALSE),"Missing")="Verified")),"Ready","Dependency open") -> Dependency open | P36: Labels and rejection reasons independently reviewed | Q36: Gold-case register | S36: 6000 | T36: J-H01 / REQ-ACT-01 | U36: Proposed work; implementation not authorized by this documentation request. | V36: Demo
A37: P02.02.02 | B37: P02 | C37: P02.02 Evaluation baseline | D37: Run rules-only baseline | E37: Evaluation reviewer | F37: Not started | G37: FALSE | H37: =IF(COUNTIFS($A$6:$A$161,A37)<>1,"Duplicate ID",IF(O37<>"Ready","Dependency open",IF(G37=TRUE,IF(AND(F37="Complete",I37<>"",J37<>"",K37<>""),"Verified","Evidence required"),IF(F37="Complete","Check completion",IF(F37="Blocked","Blocked",IF(F37="In progress","In progress",IF(F37="In review","In review","Open"))))))) -> Dependency open | L37: P02.02.01 | O37: =IF(AND(OR(L37="",IFNA(VLOOKUP(L37,$A$6:$H$36,8,FALSE),"Missing")="Verified"),OR(M37="",IFNA(VLOOKUP(M37,$A$6:$H$36,8,FALSE),"Missing")="Verified"),OR(N37="",IFNA(VLOOKUP(N37,$A$6:$H$36,8,FALSE),"Missing")="Verified")),"Ready","Dependency open") -> Dependency open | P37: Fixed input fixtures and privileges; raw results retained | Q37: Baseline run ID | S37: 6000 | T37: J-H01 / REQ-ACT-01 | U37: Proposed work; implementation not authorized by this documentation request. | V37: Demo
A38: P02.02.03 | B38: P02 | C38: P02.02 Evaluation baseline | D38: Add adversarial and concurrency assertions | E38: Evaluation reviewer | F38: Not started | G38: FALSE | H38: =IF(COUNTIFS($A$6:$A$161,A38)<>1,"Duplicate ID",IF(O38<>"Ready","Dependency open",IF(G38=TRUE,IF(AND(F38="Complete",I38<>"",J38<>"",K38<>""),"Verified","Evidence required"),IF(F38="Complete","Check completion",IF(F38="Blocked","Blocked",IF(F38="In progress","In progress",IF(F38="In review","In review","Open"))))))) -> Dependency open | L38: P02.02.02 | O38: =IF(AND(OR(L38="",IFNA(VLOOKUP(L38,$A$6:$H$37,8,FALSE),"Missing")="Verified"),OR(M38="",IFNA(VLOOKUP(M38,$A$6:$H$37,8,FALSE),"Missing")="Verified"),OR(N38="",IFNA(VLOOKUP(N38,$A$6:$H$37,8,FALSE),"Missing")="Verified")),"Ready","Dependency open") -> Dependency open | P38: Injected text, stale facts and approval races covered | Q38: Negative-case results | S38: 6000 | T38: J-H01 / REQ-ACT-01 | U38: Proposed work; implementation not authorized by this documentation request. | V38: Demo
A39: P02.02.04 | B39: P02 | C39: P02.02 Evaluation baseline | D39: Define fair comparison protocol | E39: Evaluation reviewer | F39: Not started | G39: FALSE | H39: =IF(COUNTIFS($A$6:$A$161,A39)<>1,"Duplicate ID",IF(O39<>"Ready","Dependency open",IF(G39=TRUE,IF(AND(F39="Complete",I39<>"",J39<>"",K39<>""),"Verified","Evidence required"),IF(F39="Complete","Check completion",IF(F39="Blocked","Blocked",IF(F39="In progress","In progress",IF(F39="In review","In review","Open"))))))) -> Dependency open | L39: P02.02.03 | O39: =IF(AND(OR(L39="",IFNA(VLOOKUP(L39,$A$6:$H$38,8,FALSE),"Missing")="Verified"),OR(M39="",IFNA(VLOOKUP(M39,$A$6:$H$38,8,FALSE),"Missing")="Verified"),OR(N39="",IFNA(VLOOKUP(N39,$A$6:$H$38,8,FALSE),"Missing")="Verified")),"Ready","Dependency open") -> Dependency open | P39: Equivalent inputs, model budget and reporting denominator frozen | Q39: Evaluation protocol | S39: 6000 | T39: J-H01 / REQ-ACT-01 | U39: Proposed work; implementation not authorized by this documentation request. | V39: Demo
A40: P02.03.01 | B40: P02 | C40: P02.03 Human workflow | D40: Build synthetic scenario start and actor view | E40: Frontend engineer | F40: Not started | G40: FALSE | H40: =IF(COUNTIFS($A$6:$A$161,A40)<>1,"Duplicate ID",IF(O40<>"Ready","Dependency open",IF(G40=TRUE,IF(AND(F40="Complete",I40<>"",J40<>"",K40<>""),"Verified","Evidence required"),IF(F40="Complete","Check completion",IF(F40="Blocked","Blocked",IF(F40="In progress","In progress",IF(F40="In review","In review","Open"))))))) -> Dependency open | L40: P01.90.01 | O40: =IF(AND(OR(L40="",IFNA(VLOOKUP(L40,$A$6:$H$39,8,FALSE),"Missing")="Verified"),OR(M40="",IFNA(VLOOKUP(M40,$A$6:$H$39,8,FALSE),"Missing")="Verified"),OR(N40="",IFNA(VLOOKUP(N40,$A$6:$H$39,8,FALSE),"Missing")="Verified")),"Ready","Dependency open") -> Dependency open | P40: Demo tenant and simulated records conspicuous | Q40: Scenario screen evidence | S40: 6000 | T40: J-H01 / REQ-ACT-01 | U40: Proposed work; implementation not authorized by this documentation request. | V40: Demo
A41: P02.03.02 | B41: P02 | C41: P02.03 Human workflow | D41: Build candidate/fact review interaction | E41: Frontend engineer | F41: Not started | G41: FALSE | H41: =IF(COUNTIFS($A$6:$A$161,A41)<>1,"Duplicate ID",IF(O41<>"Ready","Dependency open",IF(G41=TRUE,IF(AND(F41="Complete",I41<>"",J41<>"",K41<>""),"Verified","Evidence required"),IF(F41="Complete","Check completion",IF(F41="Blocked","Blocked",IF(F41="In progress","In progress",IF(F41="In review","In review","Open"))))))) -> Dependency open | L41: P02.03.01 | O41: =IF(AND(OR(L41="",IFNA(VLOOKUP(L41,$A$6:$H$40,8,FALSE),"Missing")="Verified"),OR(M41="",IFNA(VLOOKUP(M41,$A$6:$H$40,8,FALSE),"Missing")="Verified"),OR(N41="",IFNA(VLOOKUP(N41,$A$6:$H$40,8,FALSE),"Missing")="Verified")),"Ready","Dependency open") -> Dependency open | P41: Field changes explicit; confirm distinct from extraction | Q41: Review-flow evidence | S41: 6000 | T41: J-H01 / REQ-ACT-01 | U41: Proposed work; implementation not authorized by this documentation request. | V41: Demo
A42: P02.03.03 | B42: P02 | C42: P02.03 Human workflow | D42: Build proposal preview and approval interaction | E42: Frontend engineer | F42: Not started | G42: FALSE | H42: =IF(COUNTIFS($A$6:$A$161,A42)<>1,"Duplicate ID",IF(O42<>"Ready","Dependency open",IF(G42=TRUE,IF(AND(F42="Complete",I42<>"",J42<>"",K42<>""),"Verified","Evidence required"),IF(F42="Complete","Check completion",IF(F42="Blocked","Blocked",IF(F42="In progress","In progress",IF(F42="In review","In review","Open"))))))) -> Dependency open | L42: P02.03.02 | O42: =IF(AND(OR(L42="",IFNA(VLOOKUP(L42,$A$6:$H$41,8,FALSE),"Missing")="Verified"),OR(M42="",IFNA(VLOOKUP(M42,$A$6:$H$41,8,FALSE),"Missing")="Verified"),OR(N42="",IFNA(VLOOKUP(N42,$A$6:$H$41,8,FALSE),"Missing")="Verified")),"Ready","Dependency open") -> Dependency open | P42: Actor sees quantities, uncertainty, expiry and simulation before approving | Q42: Approval UX evidence | S42: 6000 | T42: J-H01 / REQ-ACT-01 | U42: Proposed work; implementation not authorized by this documentation request. | V42: Demo
A43: P02.03.04 | B43: P02 | C43: P02.03 Human workflow | D43: Build honest outcome journal states | E43: Frontend engineer | F43: Not started | G43: FALSE | H43: =IF(COUNTIFS($A$6:$A$161,A43)<>1,"Duplicate ID",IF(O43<>"Ready","Dependency open",IF(G43=TRUE,IF(AND(F43="Complete",I43<>"",J43<>"",K43<>""),"Verified","Evidence required"),IF(F43="Complete","Check completion",IF(F43="Blocked","Blocked",IF(F43="In progress","In progress",IF(F43="In review","In review","Open"))))))) -> Dependency open | L43: P02.03.03 | O43: =IF(AND(OR(L43="",IFNA(VLOOKUP(L43,$A$6:$H$42,8,FALSE),"Missing")="Verified"),OR(M43="",IFNA(VLOOKUP(M43,$A$6:$H$42,8,FALSE),"Missing")="Verified"),OR(N43="",IFNA(VLOOKUP(N43,$A$6:$H$42,8,FALSE),"Missing")="Verified")),"Ready","Dependency open") -> Dependency open | P43: Measured, simulated and unknown separated; loading/empty/error/retry shown | Q43: Outcome state screenshots | S43: 6000 | T43: J-H01 / REQ-ACT-01 | U43: Proposed work; implementation not authorized by this documentation request. | V43: Demo
A44: P02.90.01 | B44: P02 | C44: P02.90 Phase gate | D44: Review and accept deterministic baseline and synthetic household flow | E44: Product owner + independent reviewer | F44: Not started | G44: FALSE | H44: =IF(COUNTIFS($A$6:$A$161,A44)<>1,"Duplicate ID",IF(O44<>"Ready","Dependency open",IF(G44=TRUE,IF(AND(F44="Complete",I44<>"",J44<>"",K44<>""),"Verified","Evidence required"),IF(F44="Complete","Check completion",IF(F44="Blocked","Blocked",IF(F44="In progress","In progress",IF(F44="In review","In review","Open"))))))) -> Dependency open | L44: P02.01.04 | M44: P02.02.04 | N44: P02.03.04 | O44: =IF(AND(OR(L44="",IFNA(VLOOKUP(L44,$A$6:$H$43,8,FALSE),"Missing")="Verified"),OR(M44="",IFNA(VLOOKUP(M44,$A$6:$H$43,8,FALSE),"Missing")="Verified"),OR(N44="",IFNA(VLOOKUP(N44,$A$6:$H$43,8,FALSE),"Missing")="Verified")),"Ready","Dependency open") -> Dependency open | P44: All prerequisites verified; critical risks closed or explicitly rejected for rollout; human records go/revise/stop decision. | Q44: Phase gate record with reviewer, evidence links, residual risks and next scope | S44: 4000 | T44: P02-GATE | U44: Unchecked until phase evidence is reviewed. A written plan is not implementation evidence. | V44: Demo
A45: P03.01.01 | B45: P03 | C45: P03.01 Structured intake | D45: Verify allowed Vertex model and extraction schema | E45: AI engineer | F45: Not started | G45: FALSE | H45: =IF(COUNTIFS($A$6:$A$161,A45)<>1,"Duplicate ID",IF(O45<>"Ready","Dependency open",IF(G45=TRUE,IF(AND(F45="Complete",I45<>"",J45<>"",K45<>""),"Verified","Evidence required"),IF(F45="Complete","Check completion",IF(F45="Blocked","Blocked",IF(F45="In progress","In progress",IF(F45="In review","In review","Open"))))))) -> Dependency open | L45: P02.90.01 | O45: =IF(AND(OR(L45="",IFNA(VLOOKUP(L45,$A$6:$H$44,8,FALSE),"Missing")="Verified"),OR(M45="",IFNA(VLOOKUP(M45,$A$6:$H$44,8,FALSE),"Missing")="Verified"),OR(N45="",IFNA(VLOOKUP(N45,$A$6:$H$44,8,FALSE),"Missing")="Verified")),"Ready","Dependency open") -> Dependency open | P45: Actual model ID/region recorded; parse output constrained | Q45: Model access and schema evidence | S45: 6000 | T45: J-H01 / REQ-ACT-01 | U45: Proposed work; implementation not authorized by this documentation request. | V45: Demo
A46: P03.01.02 | B46: P03 | C46: P03.01 Structured intake | D46: Implement text intake and optional image upload | E46: AI engineer | F46: Not started | G46: FALSE | H46: =IF(COUNTIFS($A$6:$A$161,A46)<>1,"Duplicate ID",IF(O46<>"Ready","Dependency open",IF(G46=TRUE,IF(AND(F46="Complete",I46<>"",J46<>"",K46<>""),"Verified","Evidence required"),IF(F46="Complete","Check completion",IF(F46="Blocked","Blocked",IF(F46="In progress","In progress",IF(F46="In review","In review","Open"))))))) -> Dependency open | L46: P03.01.01 | O46: =IF(AND(OR(L46="",IFNA(VLOOKUP(L46,$A$6:$H$45,8,FALSE),"Missing")="Verified"),OR(M46="",IFNA(VLOOKUP(M46,$A$6:$H$45,8,FALSE),"Missing")="Verified"),OR(N46="",IFNA(VLOOKUP(N46,$A$6:$H$45,8,FALSE),"Missing")="Verified")),"Ready","Dependency open") -> Dependency open | P46: Content type/size/consent validated; optional modality can be cut | Q46: Upload/input evidence | S46: 6000 | T46: J-H01 / REQ-ACT-01 | U46: Proposed work; implementation not authorized by this documentation request. | V46: Demo
A47: P03.01.03 | B47: P03 | C47: P03.01 Structured intake | D47: Enforce candidate isolation and uncertainty | E47: AI engineer | F47: Not started | G47: FALSE | H47: =IF(COUNTIFS($A$6:$A$161,A47)<>1,"Duplicate ID",IF(O47<>"Ready","Dependency open",IF(G47=TRUE,IF(AND(F47="Complete",I47<>"",J47<>"",K47<>""),"Verified","Evidence required"),IF(F47="Complete","Check completion",IF(F47="Blocked","Blocked",IF(F47="In progress","In progress",IF(F47="In review","In review","Open"))))))) -> Dependency open | L47: P03.01.02 | O47: =IF(AND(OR(L47="",IFNA(VLOOKUP(L47,$A$6:$H$46,8,FALSE),"Missing")="Verified"),OR(M47="",IFNA(VLOOKUP(M47,$A$6:$H$46,8,FALSE),"Missing")="Verified"),OR(N47="",IFNA(VLOOKUP(N47,$A$6:$H$46,8,FALSE),"Missing")="Verified")),"Ready","Dependency open") -> Dependency open | P47: AI output never writes canonical facts; missing values remain unknown | Q47: Isolation evidence | S47: 6000 | T47: J-H01 / REQ-ACT-01 | U47: Proposed work; implementation not authorized by this documentation request. | V47: Demo
A48: P03.01.04 | B48: P03 | C48: P03.01 Structured intake | D48: Verify injection and malformed-output fallback | E48: AI engineer | F48: Not started | G48: FALSE | H48: =IF(COUNTIFS($A$6:$A$161,A48)<>1,"Duplicate ID",IF(O48<>"Ready","Dependency open",IF(G48=TRUE,IF(AND(F48="Complete",I48<>"",J48<>"",K48<>""),"Verified","Evidence required"),IF(F48="Complete","Check completion",IF(F48="Blocked","Blocked",IF(F48="In progress","In progress",IF(F48="In review","In review","Open"))))))) -> Dependency open | L48: P03.01.03 | O48: =IF(AND(OR(L48="",IFNA(VLOOKUP(L48,$A$6:$H$47,8,FALSE),"Missing")="Verified"),OR(M48="",IFNA(VLOOKUP(M48,$A$6:$H$47,8,FALSE),"Missing")="Verified"),OR(N48="",IFNA(VLOOKUP(N48,$A$6:$H$47,8,FALSE),"Missing")="Verified")),"Ready","Dependency open") -> Dependency open | P48: Receipt instructions ignored; bounded retry then human correction | Q48: Extraction adversarial results | S48: 6000 | T48: J-H01 / REQ-ACT-01 | U48: Proposed work; implementation not authorized by this documentation request. | V48: Demo
A49: P03.02.01 | B49: P03 | C49: P03.02 Agent orchestration | D49: Define minimal allowlisted tool contracts | E49: AI engineer | F49: Not started | G49: FALSE | H49: =IF(COUNTIFS($A$6:$A$161,A49)<>1,"Duplicate ID",IF(O49<>"Ready","Dependency open",IF(G49=TRUE,IF(AND(F49="Complete",I49<>"",J49<>"",K49<>""),"Verified","Evidence required"),IF(F49="Complete","Check completion",IF(F49="Blocked","Blocked",IF(F49="In progress","In progress",IF(F49="In review","In review","Open"))))))) -> Dependency open | L49: P02.90.01 | O49: =IF(AND(OR(L49="",IFNA(VLOOKUP(L49,$A$6:$H$48,8,FALSE),"Missing")="Verified"),OR(M49="",IFNA(VLOOKUP(M49,$A$6:$H$48,8,FALSE),"Missing")="Verified"),OR(N49="",IFNA(VLOOKUP(N49,$A$6:$H$48,8,FALSE),"Missing")="Verified")),"Ready","Dependency open") -> Dependency open | P49: Tools receive scoped resource IDs and checked permissions | Q49: Tool registry review | S49: 6000 | T49: J-H01 / REQ-ACT-01 | U49: Proposed work; implementation not authorized by this documentation request. | V49: Demo
A50: P03.02.02 | B50: P03 | C50: P03.02 Agent orchestration | D50: Implement bounded orchestrator run | E50: AI engineer | F50: Not started | G50: FALSE | H50: =IF(COUNTIFS($A$6:$A$161,A50)<>1,"Duplicate ID",IF(O50<>"Ready","Dependency open",IF(G50=TRUE,IF(AND(F50="Complete",I50<>"",J50<>"",K50<>""),"Verified","Evidence required"),IF(F50="Complete","Check completion",IF(F50="Blocked","Blocked",IF(F50="In progress","In progress",IF(F50="In review","In review","Open"))))))) -> Dependency open | L50: P03.02.01 | O50: =IF(AND(OR(L50="",IFNA(VLOOKUP(L50,$A$6:$H$49,8,FALSE),"Missing")="Verified"),OR(M50="",IFNA(VLOOKUP(M50,$A$6:$H$49,8,FALSE),"Missing")="Verified"),OR(N50="",IFNA(VLOOKUP(N50,$A$6:$H$49,8,FALSE),"Missing")="Verified")),"Ready","Dependency open") -> Dependency open | P50: Maximum turns/cost/deadline; no self-authorized execution | Q50: Trace with termination evidence | S50: 6000 | T50: J-H01 / REQ-ACT-01 | U50: Proposed work; implementation not authorized by this documentation request. | V50: Demo
A51: P03.02.03 | B51: P03 | C51: P03.02 Agent orchestration | D51: Bind approval to versioned proposal | E51: AI engineer | F51: Not started | G51: FALSE | H51: =IF(COUNTIFS($A$6:$A$161,A51)<>1,"Duplicate ID",IF(O51<>"Ready","Dependency open",IF(G51=TRUE,IF(AND(F51="Complete",I51<>"",J51<>"",K51<>""),"Verified","Evidence required"),IF(F51="Complete","Check completion",IF(F51="Blocked","Blocked",IF(F51="In progress","In progress",IF(F51="In review","In review","Open"))))))) -> Dependency open | L51: P03.02.02 | O51: =IF(AND(OR(L51="",IFNA(VLOOKUP(L51,$A$6:$H$50,8,FALSE),"Missing")="Verified"),OR(M51="",IFNA(VLOOKUP(M51,$A$6:$H$50,8,FALSE),"Missing")="Verified"),OR(N51="",IFNA(VLOOKUP(N51,$A$6:$H$50,8,FALSE),"Missing")="Verified")),"Ready","Dependency open") -> Dependency open | P51: Expiry, current membership, hash and facts rechecked on approval | Q51: Stale/revoked approval evidence | S51: 6000 | T51: J-H01 / REQ-ACT-01 | U51: Proposed work; implementation not authorized by this documentation request. | V51: Demo
A52: P03.02.04 | B52: P03 | C52: P03.02 Agent orchestration | D52: Make approval retries idempotent | E52: AI engineer | F52: Not started | G52: FALSE | H52: =IF(COUNTIFS($A$6:$A$161,A52)<>1,"Duplicate ID",IF(O52<>"Ready","Dependency open",IF(G52=TRUE,IF(AND(F52="Complete",I52<>"",J52<>"",K52<>""),"Verified","Evidence required"),IF(F52="Complete","Check completion",IF(F52="Blocked","Blocked",IF(F52="In progress","In progress",IF(F52="In review","In review","Open"))))))) -> Dependency open | L52: P03.02.03 | O52: =IF(AND(OR(L52="",IFNA(VLOOKUP(L52,$A$6:$H$51,8,FALSE),"Missing")="Verified"),OR(M52="",IFNA(VLOOKUP(M52,$A$6:$H$51,8,FALSE),"Missing")="Verified"),OR(N52="",IFNA(VLOOKUP(N52,$A$6:$H$51,8,FALSE),"Missing")="Verified")),"Ready","Dependency open") -> Dependency open | P52: Duplicate concurrent request yields one simulated execution | Q52: Concurrency run evidence | S52: 6000 | T52: J-H01 / REQ-ACT-01 | U52: Proposed work; implementation not authorized by this documentation request. | V52: Demo
A53: P03.03.01 | B53: P03 | C53: P03.03 Golden flow integration | D53: Connect text to review to changed meal | E53: Fullstack engineer | F53: Not started | G53: FALSE | H53: =IF(COUNTIFS($A$6:$A$161,A53)<>1,"Duplicate ID",IF(O53<>"Ready","Dependency open",IF(G53=TRUE,IF(AND(F53="Complete",I53<>"",J53<>"",K53<>""),"Verified","Evidence required"),IF(F53="Complete","Check completion",IF(F53="Blocked","Blocked",IF(F53="In progress","In progress",IF(F53="In review","In review","Open"))))))) -> Dependency open | L53: P02.90.01 | O53: =IF(AND(OR(L53="",IFNA(VLOOKUP(L53,$A$6:$H$52,8,FALSE),"Missing")="Verified"),OR(M53="",IFNA(VLOOKUP(M53,$A$6:$H$52,8,FALSE),"Missing")="Verified"),OR(N53="",IFNA(VLOOKUP(N53,$A$6:$H$52,8,FALSE),"Missing")="Verified")),"Ready","Dependency open") -> Dependency open | P53: Real Gemini response goes through explicit human confirmation | Q53: J-H01 trace | S53: 6000 | T53: J-H01 / REQ-ACT-01 | U53: Proposed work; implementation not authorized by this documentation request. | V53: Demo
A54: P03.03.02 | B54: P03 | C54: P03.03 Golden flow integration | D54: Connect proposal to mock action to evidence | E54: Fullstack engineer | F54: Not started | G54: FALSE | H54: =IF(COUNTIFS($A$6:$A$161,A54)<>1,"Duplicate ID",IF(O54<>"Ready","Dependency open",IF(G54=TRUE,IF(AND(F54="Complete",I54<>"",J54<>"",K54<>""),"Verified","Evidence required"),IF(F54="Complete","Check completion",IF(F54="Blocked","Blocked",IF(F54="In progress","In progress",IF(F54="In review","In review","Open"))))))) -> Dependency open | L54: P03.03.01 | O54: =IF(AND(OR(L54="",IFNA(VLOOKUP(L54,$A$6:$H$53,8,FALSE),"Missing")="Verified"),OR(M54="",IFNA(VLOOKUP(M54,$A$6:$H$53,8,FALSE),"Missing")="Verified"),OR(N54="",IFNA(VLOOKUP(N54,$A$6:$H$53,8,FALSE),"Missing")="Verified")),"Ready","Dependency open") -> Dependency open | P54: No real checkout or dispatch; visible simulated outcome | Q54: J-H01 full-flow recording | S54: 6000 | T54: J-H01 / REQ-ACT-01 | U54: Proposed work; implementation not authorized by this documentation request. | V54: Demo
A55: P03.03.03 | B55: P03 | C55: P03.03 Golden flow integration | D55: Handle connectivity and cancellation | E55: Fullstack engineer | F55: Not started | G55: FALSE | H55: =IF(COUNTIFS($A$6:$A$161,A55)<>1,"Duplicate ID",IF(O55<>"Ready","Dependency open",IF(G55=TRUE,IF(AND(F55="Complete",I55<>"",J55<>"",K55<>""),"Verified","Evidence required"),IF(F55="Complete","Check completion",IF(F55="Blocked","Blocked",IF(F55="In progress","In progress",IF(F55="In review","In review","Open"))))))) -> Dependency open | L55: P03.03.02 | O55: =IF(AND(OR(L55="",IFNA(VLOOKUP(L55,$A$6:$H$54,8,FALSE),"Missing")="Verified"),OR(M55="",IFNA(VLOOKUP(M55,$A$6:$H$54,8,FALSE),"Missing")="Verified"),OR(N55="",IFNA(VLOOKUP(N55,$A$6:$H$54,8,FALSE),"Missing")="Verified")),"Ready","Dependency open") -> Dependency open | P55: Resume from persisted state; ambiguous action state reconciled | Q55: Recovery-flow evidence | S55: 6000 | T55: J-H01 / REQ-ACT-01 | U55: Proposed work; implementation not authorized by this documentation request. | V55: Demo
A56: P03.03.04 | B56: P03 | C56: P03.03 Golden flow integration | D56: Compare against rules and plain Gemini | E56: Fullstack engineer | F56: Not started | G56: FALSE | H56: =IF(COUNTIFS($A$6:$A$161,A56)<>1,"Duplicate ID",IF(O56<>"Ready","Dependency open",IF(G56=TRUE,IF(AND(F56="Complete",I56<>"",J56<>"",K56<>""),"Verified","Evidence required"),IF(F56="Complete","Check completion",IF(F56="Blocked","Blocked",IF(F56="In progress","In progress",IF(F56="In review","In review","Open"))))))) -> Dependency open | L56: P03.03.03 | O56: =IF(AND(OR(L56="",IFNA(VLOOKUP(L56,$A$6:$H$55,8,FALSE),"Missing")="Verified"),OR(M56="",IFNA(VLOOKUP(M56,$A$6:$H$55,8,FALSE),"Missing")="Verified"),OR(N56="",IFNA(VLOOKUP(N56,$A$6:$H$55,8,FALSE),"Missing")="Verified")),"Ready","Dependency open") -> Dependency open | P56: Correctness/unsafe actions/latency/effort reported with run IDs | Q56: Paired benchmark results | S56: 6000 | T56: J-H01 / REQ-ACT-01 | U56: Proposed work; implementation not authorized by this documentation request. | V56: Demo
A57: P03.90.01 | B57: P03 | C57: P03.90 Phase gate | D57: Review and accept gemini intake and single-orchestrator household journey | E57: Product owner + independent reviewer | F57: Not started | G57: FALSE | H57: =IF(COUNTIFS($A$6:$A$161,A57)<>1,"Duplicate ID",IF(O57<>"Ready","Dependency open",IF(G57=TRUE,IF(AND(F57="Complete",I57<>"",J57<>"",K57<>""),"Verified","Evidence required"),IF(F57="Complete","Check completion",IF(F57="Blocked","Blocked",IF(F57="In progress","In progress",IF(F57="In review","In review","Open"))))))) -> Dependency open | L57: P03.01.04 | M57: P03.02.04 | N57: P03.03.04 | O57: =IF(AND(OR(L57="",IFNA(VLOOKUP(L57,$A$6:$H$56,8,FALSE),"Missing")="Verified"),OR(M57="",IFNA(VLOOKUP(M57,$A$6:$H$56,8,FALSE),"Missing")="Verified"),OR(N57="",IFNA(VLOOKUP(N57,$A$6:$H$56,8,FALSE),"Missing")="Verified")),"Ready","Dependency open") -> Dependency open | P57: All prerequisites verified; critical risks closed or explicitly rejected for rollout; human records go/revise/stop decision. | Q57: Phase gate record with reviewer, evidence links, residual risks and next scope | S57: 4000 | T57: P03-GATE | U57: Unchecked until phase evidence is reviewed. A written plan is not implementation evidence. | V57: Demo
A58: P04.01.01 | B58: P04 | C58: P04.01 Deploy core | D58: Prepare App Hosting and Cloud Run manifests | E58: Platform engineer | F58: Not started | G58: FALSE | H58: =IF(COUNTIFS($A$6:$A$161,A58)<>1,"Duplicate ID",IF(O58<>"Ready","Dependency open",IF(G58=TRUE,IF(AND(F58="Complete",I58<>"",J58<>"",K58<>""),"Verified","Evidence required"),IF(F58="Complete","Check completion",IF(F58="Blocked","Blocked",IF(F58="In progress","In progress",IF(F58="In review","In review","Open"))))))) -> Dependency open | L58: P03.90.01 | O58: =IF(AND(OR(L58="",IFNA(VLOOKUP(L58,$A$6:$H$57,8,FALSE),"Missing")="Verified"),OR(M58="",IFNA(VLOOKUP(M58,$A$6:$H$57,8,FALSE),"Missing")="Verified"),OR(N58="",IFNA(VLOOKUP(N58,$A$6:$H$57,8,FALSE),"Missing")="Verified")),"Ready","Dependency open") -> Dependency open | P58: Pinned runtime, secrets references and service identities reviewed | Q58: Deployment config review | S58: 6000 | T58: REQ-DEPLOY-01 | U58: Proposed work; implementation not authorized by this documentation request. | V58: Demo
A59: P04.01.02 | B59: P04 | C59: P04.01 Deploy core | D59: Deploy isolated demo environment | E59: Platform engineer | F59: Not started | G59: FALSE | H59: =IF(COUNTIFS($A$6:$A$161,A59)<>1,"Duplicate ID",IF(O59<>"Ready","Dependency open",IF(G59=TRUE,IF(AND(F59="Complete",I59<>"",J59<>"",K59<>""),"Verified","Evidence required"),IF(F59="Complete","Check completion",IF(F59="Blocked","Blocked",IF(F59="In progress","In progress",IF(F59="In review","In review","Open"))))))) -> Dependency open | L59: P04.01.01 | O59: =IF(AND(OR(L59="",IFNA(VLOOKUP(L59,$A$6:$H$58,8,FALSE),"Missing")="Verified"),OR(M59="",IFNA(VLOOKUP(M59,$A$6:$H$58,8,FALSE),"Missing")="Verified"),OR(N59="",IFNA(VLOOKUP(N59,$A$6:$H$58,8,FALSE),"Missing")="Verified")),"Ready","Dependency open") -> Dependency open | P59: Public app URL and secured backend reachable; no real private data | Q59: Deployment URLs and revision IDs | S59: 6000 | T59: REQ-DEPLOY-01 | U59: Proposed work; implementation not authorized by this documentation request. | V59: Demo
A60: P04.01.03 | B60: P04 | C60: P04.01 Deploy core | D60: Verify cross-service authentication and health | E60: Platform engineer | F60: Not started | G60: FALSE | H60: =IF(COUNTIFS($A$6:$A$161,A60)<>1,"Duplicate ID",IF(O60<>"Ready","Dependency open",IF(G60=TRUE,IF(AND(F60="Complete",I60<>"",J60<>"",K60<>""),"Verified","Evidence required"),IF(F60="Complete","Check completion",IF(F60="Blocked","Blocked",IF(F60="In progress","In progress",IF(F60="In review","In review","Open"))))))) -> Dependency open | L60: P04.01.02 | O60: =IF(AND(OR(L60="",IFNA(VLOOKUP(L60,$A$6:$H$59,8,FALSE),"Missing")="Verified"),OR(M60="",IFNA(VLOOKUP(M60,$A$6:$H$59,8,FALSE),"Missing")="Verified"),OR(N60="",IFNA(VLOOKUP(N60,$A$6:$H$59,8,FALSE),"Missing")="Verified")),"Ready","Dependency open") -> Dependency open | P60: Anonymous mutation and foreign tenant access fail on deployed system | Q60: Deployed negative checks | S60: 6000 | T60: REQ-DEPLOY-01 | U60: Proposed work; implementation not authorized by this documentation request. | V60: Demo
A61: P04.01.04 | B61: P04 | C61: P04.01 Deploy core | D61: Prove rollback and degraded mode | E61: Platform engineer | F61: Not started | G61: FALSE | H61: =IF(COUNTIFS($A$6:$A$161,A61)<>1,"Duplicate ID",IF(O61<>"Ready","Dependency open",IF(G61=TRUE,IF(AND(F61="Complete",I61<>"",J61<>"",K61<>""),"Verified","Evidence required"),IF(F61="Complete","Check completion",IF(F61="Blocked","Blocked",IF(F61="In progress","In progress",IF(F61="In review","In review","Open"))))))) -> Dependency open | L61: P04.01.03 | O61: =IF(AND(OR(L61="",IFNA(VLOOKUP(L61,$A$6:$H$60,8,FALSE),"Missing")="Verified"),OR(M61="",IFNA(VLOOKUP(M61,$A$6:$H$60,8,FALSE),"Missing")="Verified"),OR(N61="",IFNA(VLOOKUP(N61,$A$6:$H$60,8,FALSE),"Missing")="Verified")),"Ready","Dependency open") -> Dependency open | P61: Prior revision recoverable; model outage visibly handled | Q61: Rollback/degraded evidence | S61: 6000 | T61: REQ-DEPLOY-01 | U61: Proposed work; implementation not authorized by this documentation request. | V61: Demo
A62: P04.02.01 | B62: P04 | C62: P04.02 Release checks | D62: Verify end-to-end mobile flow | E62: Evaluation reviewer | F62: Not started | G62: FALSE | H62: =IF(COUNTIFS($A$6:$A$161,A62)<>1,"Duplicate ID",IF(O62<>"Ready","Dependency open",IF(G62=TRUE,IF(AND(F62="Complete",I62<>"",J62<>"",K62<>""),"Verified","Evidence required"),IF(F62="Complete","Check completion",IF(F62="Blocked","Blocked",IF(F62="In progress","In progress",IF(F62="In review","In review","Open"))))))) -> Dependency open | L62: P03.90.01 | O62: =IF(AND(OR(L62="",IFNA(VLOOKUP(L62,$A$6:$H$61,8,FALSE),"Missing")="Verified"),OR(M62="",IFNA(VLOOKUP(M62,$A$6:$H$61,8,FALSE),"Missing")="Verified"),OR(N62="",IFNA(VLOOKUP(N62,$A$6:$H$61,8,FALSE),"Missing")="Verified")),"Ready","Dependency open") -> Dependency open | P62: 360px flow, keyboard focus, labels, 44px targets and all states reviewed | Q62: Browser evidence | S62: 6000 | T62: REQ-DEPLOY-01 | U62: Proposed work; implementation not authorized by this documentation request. | V62: Demo
A63: P04.02.02 | B63: P04 | C63: P04.02 Release checks | D63: Record actual performance and cost | E63: Evaluation reviewer | F63: Not started | G63: FALSE | H63: =IF(COUNTIFS($A$6:$A$161,A63)<>1,"Duplicate ID",IF(O63<>"Ready","Dependency open",IF(G63=TRUE,IF(AND(F63="Complete",I63<>"",J63<>"",K63<>""),"Verified","Evidence required"),IF(F63="Complete","Check completion",IF(F63="Blocked","Blocked",IF(F63="In progress","In progress",IF(F63="In review","In review","Open"))))))) -> Dependency open | L63: P04.02.01 | O63: =IF(AND(OR(L63="",IFNA(VLOOKUP(L63,$A$6:$H$62,8,FALSE),"Missing")="Verified"),OR(M63="",IFNA(VLOOKUP(M63,$A$6:$H$62,8,FALSE),"Missing")="Verified"),OR(N63="",IFNA(VLOOKUP(N63,$A$6:$H$62,8,FALSE),"Missing")="Verified")),"Ready","Dependency open") -> Dependency open | P63: P50/P95, model tokens, errors and cold-start caveat measured | Q63: Run-specific metrics | S63: 6000 | T63: REQ-DEPLOY-01 | U63: Proposed work; implementation not authorized by this documentation request. | V63: Demo
A64: P04.02.03 | B64: P04 | C64: P04.02 Release checks | D64: Audit public repo and demo claims | E64: Evaluation reviewer | F64: Not started | G64: FALSE | H64: =IF(COUNTIFS($A$6:$A$161,A64)<>1,"Duplicate ID",IF(O64<>"Ready","Dependency open",IF(G64=TRUE,IF(AND(F64="Complete",I64<>"",J64<>"",K64<>""),"Verified","Evidence required"),IF(F64="Complete","Check completion",IF(F64="Blocked","Blocked",IF(F64="In progress","In progress",IF(F64="In review","In review","Open"))))))) -> Dependency open | L64: P04.02.02 | O64: =IF(AND(OR(L64="",IFNA(VLOOKUP(L64,$A$6:$H$63,8,FALSE),"Missing")="Verified"),OR(M64="",IFNA(VLOOKUP(M64,$A$6:$H$63,8,FALSE),"Missing")="Verified"),OR(N64="",IFNA(VLOOKUP(N64,$A$6:$H$63,8,FALSE),"Missing")="Verified")),"Ready","Dependency open") -> Dependency open | P64: Secrets, real data, unsupported impact and third-party rights reviewed | Q64: Release review record | S64: 6000 | T64: REQ-DEPLOY-01 | U64: Proposed work; implementation not authorized by this documentation request. | V64: Demo
A65: P04.02.04 | B65: P04 | C65: P04.02 Release checks | D65: Review all critical failures | E65: Evaluation reviewer | F65: Not started | G65: FALSE | H65: =IF(COUNTIFS($A$6:$A$161,A65)<>1,"Duplicate ID",IF(O65<>"Ready","Dependency open",IF(G65=TRUE,IF(AND(F65="Complete",I65<>"",J65<>"",K65<>""),"Verified","Evidence required"),IF(F65="Complete","Check completion",IF(F65="Blocked","Blocked",IF(F65="In progress","In progress",IF(F65="In review","In review","Open"))))))) -> Dependency open | L65: P04.02.03 | O65: =IF(AND(OR(L65="",IFNA(VLOOKUP(L65,$A$6:$H$64,8,FALSE),"Missing")="Verified"),OR(M65="",IFNA(VLOOKUP(M65,$A$6:$H$64,8,FALSE),"Missing")="Verified"),OR(N65="",IFNA(VLOOKUP(N65,$A$6:$H$64,8,FALSE),"Missing")="Verified")),"Ready","Dependency open") -> Dependency open | P65: No unowned critical auth/safety/data-loss failure accepted | Q65: Critical issue disposition | S65: 6000 | T65: REQ-DEPLOY-01 | U65: Proposed work; implementation not authorized by this documentation request. | V65: Demo
A66: P04.03.01 | B66: P04 | C66: P04.03 Submission assets | D66: Prepare final proposal document and deck content | E66: Product owner | F66: Not started | G66: FALSE | H66: =IF(COUNTIFS($A$6:$A$161,A66)<>1,"Duplicate ID",IF(O66<>"Ready","Dependency open",IF(G66=TRUE,IF(AND(F66="Complete",I66<>"",J66<>"",K66<>""),"Verified","Evidence required"),IF(F66="Complete","Check completion",IF(F66="Blocked","Blocked",IF(F66="In progress","In progress",IF(F66="In review","In review","Open"))))))) -> Dependency open | L66: P03.90.01 | O66: =IF(AND(OR(L66="",IFNA(VLOOKUP(L66,$A$6:$H$65,8,FALSE),"Missing")="Verified"),OR(M66="",IFNA(VLOOKUP(M66,$A$6:$H$65,8,FALSE),"Missing")="Verified"),OR(N66="",IFNA(VLOOKUP(N66,$A$6:$H$65,8,FALSE),"Missing")="Verified")),"Ready","Dependency open") -> Dependency open | P66: Problem, Google AI role, evidence and limitations align with working demo | Q66: Proposal/PDF artifact | S66: 6000 | T66: REQ-DEPLOY-01 | U66: Proposed work; implementation not authorized by this documentation request. | V66: Demo
A67: P04.03.02 | B67: P04 | C67: P04.03 Submission assets | D67: Record strictly under-three-minute demo | E67: Product owner | F67: Not started | G67: FALSE | H67: =IF(COUNTIFS($A$6:$A$161,A67)<>1,"Duplicate ID",IF(O67<>"Ready","Dependency open",IF(G67=TRUE,IF(AND(F67="Complete",I67<>"",J67<>"",K67<>""),"Verified","Evidence required"),IF(F67="Complete","Check completion",IF(F67="Blocked","Blocked",IF(F67="In progress","In progress",IF(F67="In review","In review","Open"))))))) -> Dependency open | L67: P04.03.01 | O67: =IF(AND(OR(L67="",IFNA(VLOOKUP(L67,$A$6:$H$66,8,FALSE),"Missing")="Verified"),OR(M67="",IFNA(VLOOKUP(M67,$A$6:$H$66,8,FALSE),"Missing")="Verified"),OR(N67="",IFNA(VLOOKUP(N67,$A$6:$H$66,8,FALSE),"Missing")="Verified")),"Ready","Dependency open") -> Dependency open | P67: Public access checked; live behavior and simulations identified | Q67: Final video link/duration | S67: 6000 | T67: REQ-DEPLOY-01 | U67: Proposed work; implementation not authorized by this documentation request. | V67: Demo
A68: P04.03.03 | B68: P04 | C68: P04.03 Submission assets | D68: Validate submission packet and eligibility | E68: Product owner | F68: Not started | G68: FALSE | H68: =IF(COUNTIFS($A$6:$A$161,A68)<>1,"Duplicate ID",IF(O68<>"Ready","Dependency open",IF(G68=TRUE,IF(AND(F68="Complete",I68<>"",J68<>"",K68<>""),"Verified","Evidence required"),IF(F68="Complete","Check completion",IF(F68="Blocked","Blocked",IF(F68="In progress","In progress",IF(F68="In review","In review","Open"))))))) -> Dependency open | L68: P04.03.02 | O68: =IF(AND(OR(L68="",IFNA(VLOOKUP(L68,$A$6:$H$67,8,FALSE),"Missing")="Verified"),OR(M68="",IFNA(VLOOKUP(M68,$A$6:$H$67,8,FALSE),"Missing")="Verified"),OR(N68="",IFNA(VLOOKUP(N68,$A$6:$H$67,8,FALSE),"Missing")="Verified")),"Ready","Dependency open") -> Dependency open | P68: Repository, URL, deck, video, track and roster checked against live terms | Q68: Submission checklist | S68: 6000 | T68: REQ-DEPLOY-01 | U68: Proposed work; implementation not authorized by this documentation request. | V68: Demo
A69: P04.03.04 | B69: P04 | C69: P04.03 Submission assets | D69: Submit and retain receipt | E69: Product owner | F69: Not started | G69: FALSE | H69: =IF(COUNTIFS($A$6:$A$161,A69)<>1,"Duplicate ID",IF(O69<>"Ready","Dependency open",IF(G69=TRUE,IF(AND(F69="Complete",I69<>"",J69<>"",K69<>""),"Verified","Evidence required"),IF(F69="Complete","Check completion",IF(F69="Blocked","Blocked",IF(F69="In progress","In progress",IF(F69="In review","In review","Open"))))))) -> Dependency open | L69: P04.03.03 | O69: =IF(AND(OR(L69="",IFNA(VLOOKUP(L69,$A$6:$H$68,8,FALSE),"Missing")="Verified"),OR(M69="",IFNA(VLOOKUP(M69,$A$6:$H$68,8,FALSE),"Missing")="Verified"),OR(N69="",IFNA(VLOOKUP(N69,$A$6:$H$68,8,FALSE),"Missing")="Verified")),"Ready","Dependency open") -> Dependency open | P69: Authorized human submits before confirmed cutoff; receipt retained | Q69: Submission confirmation | S69: 6000 | T69: REQ-DEPLOY-01 | U69: Proposed work; implementation not authorized by this documentation request. | V69: Demo
A70: P04.90.01 | B70: P04 | C70: P04.90 Phase gate | D70: Review and accept google deployment and submission readiness | E70: Product owner + independent reviewer | F70: Not started | G70: FALSE | H70: =IF(COUNTIFS($A$6:$A$161,A70)<>1,"Duplicate ID",IF(O70<>"Ready","Dependency open",IF(G70=TRUE,IF(AND(F70="Complete",I70<>"",J70<>"",K70<>""),"Verified","Evidence required"),IF(F70="Complete","Check completion",IF(F70="Blocked","Blocked",IF(F70="In progress","In progress",IF(F70="In review","In review","Open"))))))) -> Dependency open | L70: P04.01.04 | M70: P04.02.04 | N70: P04.03.04 | O70: =IF(AND(OR(L70="",IFNA(VLOOKUP(L70,$A$6:$H$69,8,FALSE),"Missing")="Verified"),OR(M70="",IFNA(VLOOKUP(M70,$A$6:$H$69,8,FALSE),"Missing")="Verified"),OR(N70="",IFNA(VLOOKUP(N70,$A$6:$H$69,8,FALSE),"Missing")="Verified")),"Ready","Dependency open") -> Dependency open | P70: All prerequisites verified; critical risks closed or explicitly rejected for rollout; human records go/revise/stop decision. | Q70: Phase gate record with reviewer, evidence links, residual risks and next scope | S70: 4000 | T70: P04-GATE | U70: Unchecked until phase evidence is reviewed. A written plan is not implementation evidence. | V70: Demo
A71: P05.01.01 | B71: P05 | C71: P05.01 Roster and preparation authority | D71: Map kitchen roles and source authority | E71: Product/backend team | F71: Not started | G71: FALSE | H71: =IF(COUNTIFS($A$6:$A$161,A71)<>1,"Duplicate ID",IF(O71<>"Ready","Dependency open",IF(G71=TRUE,IF(AND(F71="Complete",I71<>"",J71<>"",K71<>""),"Verified","Evidence required"),IF(F71="Complete","Check completion",IF(F71="Blocked","Blocked",IF(F71="In progress","In progress",IF(F71="In review","In review","Open"))))))) -> Dependency open | L71: P04.90.01 | O71: =IF(AND(OR(L71="",IFNA(VLOOKUP(L71,$A$6:$H$70,8,FALSE),"Missing")="Verified"),OR(M71="",IFNA(VLOOKUP(M71,$A$6:$H$70,8,FALSE),"Missing")="Verified"),OR(N71="",IFNA(VLOOKUP(N71,$A$6:$H$70,8,FALSE),"Missing")="Verified")),"Ready","Dependency open") -> Dependency open | P71: Headcount reporter cannot override chef/menu policy | Q71: J-K01 role map | S71: 6000 | T71: J-K01 | U71: Proposed work; implementation not authorized by this documentation request. | V71: Expansion
A72: P05.01.02 | B72: P05 | C72: P05.01 Roster and preparation authority | D72: Model per-batch last reversible point | E72: Product/backend team | F72: Not started | G72: FALSE | H72: =IF(COUNTIFS($A$6:$A$161,A72)<>1,"Duplicate ID",IF(O72<>"Ready","Dependency open",IF(G72=TRUE,IF(AND(F72="Complete",I72<>"",J72<>"",K72<>""),"Verified","Evidence required"),IF(F72="Complete","Check completion",IF(F72="Blocked","Blocked",IF(F72="In progress","In progress",IF(F72="In review","In review","Open"))))))) -> Dependency open | L72: P05.01.01 | O72: =IF(AND(OR(L72="",IFNA(VLOOKUP(L72,$A$6:$H$71,8,FALSE),"Missing")="Verified"),OR(M72="",IFNA(VLOOKUP(M72,$A$6:$H$71,8,FALSE),"Missing")="Verified"),OR(N72="",IFNA(VLOOKUP(N72,$A$6:$H$71,8,FALSE),"Missing")="Verified")),"Ready","Dependency open") -> Dependency open | P72: Chef-specified timestamp/timezone/version; no universal 45-minute rule | Q72: Batch/cutoff contract | S72: 6000 | T72: J-K01 | U72: Proposed work; implementation not authorized by this documentation request. | V72: Expansion
A73: P05.01.03 | B73: P05 | C73: P05.01 Roster and preparation authority | D73: Capture and confirm attendance exceptions | E73: Product/backend team | F73: Not started | G73: FALSE | H73: =IF(COUNTIFS($A$6:$A$161,A73)<>1,"Duplicate ID",IF(O73<>"Ready","Dependency open",IF(G73=TRUE,IF(AND(F73="Complete",I73<>"",J73<>"",K73<>""),"Verified","Evidence required"),IF(F73="Complete","Check completion",IF(F73="Blocked","Blocked",IF(F73="In progress","In progress",IF(F73="In review","In review","Open"))))))) -> Dependency open | L73: P05.01.02 | O73: =IF(AND(OR(L73="",IFNA(VLOOKUP(L73,$A$6:$H$72,8,FALSE),"Missing")="Verified"),OR(M73="",IFNA(VLOOKUP(M73,$A$6:$H$72,8,FALSE),"Missing")="Verified"),OR(N73="",IFNA(VLOOKUP(N73,$A$6:$H$72,8,FALSE),"Missing")="Verified")),"Ready","Dependency open") -> Dependency open | P73: Changes record source, effective date and approved diners | Q73: Roster change evidence | S73: 6000 | T73: J-K01 | U73: Proposed work; implementation not authorized by this documentation request. | V73: Expansion
A74: P05.01.04 | B74: P05 | C74: P05.01 Roster and preparation authority | D74: Reject late and conflicting adjustments | E74: Product/backend team | F74: Not started | G74: FALSE | H74: =IF(COUNTIFS($A$6:$A$161,A74)<>1,"Duplicate ID",IF(O74<>"Ready","Dependency open",IF(G74=TRUE,IF(AND(F74="Complete",I74<>"",J74<>"",K74<>""),"Verified","Evidence required"),IF(F74="Complete","Check completion",IF(F74="Blocked","Blocked",IF(F74="In progress","In progress",IF(F74="In review","In review","Open"))))))) -> Dependency open | L74: P05.01.03 | O74: =IF(AND(OR(L74="",IFNA(VLOOKUP(L74,$A$6:$H$73,8,FALSE),"Missing")="Verified"),OR(M74="",IFNA(VLOOKUP(M74,$A$6:$H$73,8,FALSE),"Missing")="Verified"),OR(N74="",IFNA(VLOOKUP(N74,$A$6:$H$73,8,FALSE),"Missing")="Verified")),"Ready","Dependency open") -> Dependency open | P74: Already-started/closed batch yields hold or new human decision | Q74: Cutoff/concurrency cases | S74: 6000 | T74: J-K01 | U74: Proposed work; implementation not authorized by this documentation request. | V74: Expansion
A75: P05.02.01 | B75: P05 | C75: P05.02 Chef and measurements | D75: Review dietary and nutrition constraints | E75: Kitchen partner lead | F75: Not started | G75: FALSE | H75: =IF(COUNTIFS($A$6:$A$161,A75)<>1,"Duplicate ID",IF(O75<>"Ready","Dependency open",IF(G75=TRUE,IF(AND(F75="Complete",I75<>"",J75<>"",K75<>""),"Verified","Evidence required"),IF(F75="Complete","Check completion",IF(F75="Blocked","Blocked",IF(F75="In progress","In progress",IF(F75="In review","In review","Open"))))))) -> Dependency open | L75: P04.90.01 | O75: =IF(AND(OR(L75="",IFNA(VLOOKUP(L75,$A$6:$H$74,8,FALSE),"Missing")="Verified"),OR(M75="",IFNA(VLOOKUP(M75,$A$6:$H$74,8,FALSE),"Missing")="Verified"),OR(N75="",IFNA(VLOOKUP(N75,$A$6:$H$74,8,FALSE),"Missing")="Verified")),"Ready","Dependency open") -> Dependency open | P75: Qualified operator owns approved menu and substitutions | Q75: Operator-reviewed policy | S75: 6000 | T75: J-K01 | U75: Proposed work; implementation not authorized by this documentation request. | V75: Expansion
A76: P05.02.02 | B76: P05 | C76: P05.02 Chef and measurements | D76: Implement chef approval of batch changes | E76: Kitchen partner lead | F76: Not started | G76: FALSE | H76: =IF(COUNTIFS($A$6:$A$161,A76)<>1,"Duplicate ID",IF(O76<>"Ready","Dependency open",IF(G76=TRUE,IF(AND(F76="Complete",I76<>"",J76<>"",K76<>""),"Verified","Evidence required"),IF(F76="Complete","Check completion",IF(F76="Blocked","Blocked",IF(F76="In progress","In progress",IF(F76="In review","In review","Open"))))))) -> Dependency open | L76: P05.02.01 | O76: =IF(AND(OR(L76="",IFNA(VLOOKUP(L76,$A$6:$H$75,8,FALSE),"Missing")="Verified"),OR(M76="",IFNA(VLOOKUP(M76,$A$6:$H$75,8,FALSE),"Missing")="Verified"),OR(N76="",IFNA(VLOOKUP(N76,$A$6:$H$75,8,FALSE),"Missing")="Verified")),"Ready","Dependency open") -> Dependency open | P76: Arithmetic deterministic; prep change requires authorized chef | Q76: Chef approval trace | S76: 6000 | T76: J-K01 | U76: Proposed work; implementation not authorized by this documentation request. | V76: Expansion
A77: P05.02.03 | B77: P05 | C77: P05.02 Chef and measurements | D77: Separate preparation unserved and plate weights | E77: Kitchen partner lead | F77: Not started | G77: FALSE | H77: =IF(COUNTIFS($A$6:$A$161,A77)<>1,"Duplicate ID",IF(O77<>"Ready","Dependency open",IF(G77=TRUE,IF(AND(F77="Complete",I77<>"",J77<>"",K77<>""),"Verified","Evidence required"),IF(F77="Complete","Check completion",IF(F77="Blocked","Blocked",IF(F77="In progress","In progress",IF(F77="In review","In review","Open"))))))) -> Dependency open | L77: P05.02.02 | O77: =IF(AND(OR(L77="",IFNA(VLOOKUP(L77,$A$6:$H$76,8,FALSE),"Missing")="Verified"),OR(M77="",IFNA(VLOOKUP(M77,$A$6:$H$76,8,FALSE),"Missing")="Verified"),OR(N77="",IFNA(VLOOKUP(N77,$A$6:$H$76,8,FALSE),"Missing")="Verified")),"Ready","Dependency open") -> Dependency open | P77: Scale/time/tare/category metadata recorded distinctly | Q77: Stage measurement records | S77: 6000 | T77: J-K01 | U77: Proposed work; implementation not authorized by this documentation request. | V77: Expansion
A78: P05.02.04 | B78: P05 | C78: P05.02 Chef and measurements | D78: Reconcile planned versus actual served meals | E78: Kitchen partner lead | F78: Not started | G78: FALSE | H78: =IF(COUNTIFS($A$6:$A$161,A78)<>1,"Duplicate ID",IF(O78<>"Ready","Dependency open",IF(G78=TRUE,IF(AND(F78="Complete",I78<>"",J78<>"",K78<>""),"Verified","Evidence required"),IF(F78="Complete","Check completion",IF(F78="Blocked","Blocked",IF(F78="In progress","In progress",IF(F78="In review","In review","Open"))))))) -> Dependency open | L78: P05.02.03 | O78: =IF(AND(OR(L78="",IFNA(VLOOKUP(L78,$A$6:$H$77,8,FALSE),"Missing")="Verified"),OR(M78="",IFNA(VLOOKUP(M78,$A$6:$H$77,8,FALSE),"Missing")="Verified"),OR(N78="",IFNA(VLOOKUP(N78,$A$6:$H$77,8,FALSE),"Missing")="Verified")),"Ready","Dependency open") -> Dependency open | P78: Denominator actual served; unknown data not inferred | Q78: Kitchen outcome calculation | S78: 6000 | T78: J-K01 | U78: Proposed work; implementation not authorized by this documentation request. | V78: Expansion
A79: P05.03.01 | B79: P05 | C79: P05.03 Kitchen validation | D79: Annotate K-lane failure cases | E79: Evaluation reviewer | F79: Not started | G79: FALSE | H79: =IF(COUNTIFS($A$6:$A$161,A79)<>1,"Duplicate ID",IF(O79<>"Ready","Dependency open",IF(G79=TRUE,IF(AND(F79="Complete",I79<>"",J79<>"",K79<>""),"Verified","Evidence required"),IF(F79="Complete","Check completion",IF(F79="Blocked","Blocked",IF(F79="In progress","In progress",IF(F79="In review","In review","Open"))))))) -> Dependency open | L79: P04.90.01 | O79: =IF(AND(OR(L79="",IFNA(VLOOKUP(L79,$A$6:$H$78,8,FALSE),"Missing")="Verified"),OR(M79="",IFNA(VLOOKUP(M79,$A$6:$H$78,8,FALSE),"Missing")="Verified"),OR(N79="",IFNA(VLOOKUP(N79,$A$6:$H$78,8,FALSE),"Missing")="Verified")),"Ready","Dependency open") -> Dependency open | P79: Late event, diet mismatch, role escalation and double count covered | Q79: K gold cases | S79: 6000 | T79: J-K01 | U79: Proposed work; implementation not authorized by this documentation request. | V79: Expansion
A80: P05.03.02 | B80: P05 | C80: P05.03 Kitchen validation | D80: Compare against simple headcount and batch rules | E80: Evaluation reviewer | F80: Not started | G80: FALSE | H80: =IF(COUNTIFS($A$6:$A$161,A80)<>1,"Duplicate ID",IF(O80<>"Ready","Dependency open",IF(G80=TRUE,IF(AND(F80="Complete",I80<>"",J80<>"",K80<>""),"Verified","Evidence required"),IF(F80="Complete","Check completion",IF(F80="Blocked","Blocked",IF(F80="In progress","In progress",IF(F80="In review","In review","Open"))))))) -> Dependency open | L80: P05.03.01 | O80: =IF(AND(OR(L80="",IFNA(VLOOKUP(L80,$A$6:$H$79,8,FALSE),"Missing")="Verified"),OR(M80="",IFNA(VLOOKUP(M80,$A$6:$H$79,8,FALSE),"Missing")="Verified"),OR(N80="",IFNA(VLOOKUP(N80,$A$6:$H$79,8,FALSE),"Missing")="Verified")),"Ready","Dependency open") -> Dependency open | P80: Equivalent roster and cutoff inputs used across arms | Q80: K comparative run | S80: 6000 | T80: J-K01 | U80: Proposed work; implementation not authorized by this documentation request. | V80: Expansion
A81: P05.03.03 | B81: P05 | C81: P05.03 Kitchen validation | D81: Pilot with authorized kitchen | E81: Evaluation reviewer | F81: Not started | G81: FALSE | H81: =IF(COUNTIFS($A$6:$A$161,A81)<>1,"Duplicate ID",IF(O81<>"Ready","Dependency open",IF(G81=TRUE,IF(AND(F81="Complete",I81<>"",J81<>"",K81<>""),"Verified","Evidence required"),IF(F81="Complete","Check completion",IF(F81="Blocked","Blocked",IF(F81="In progress","In progress",IF(F81="In review","In review","Open"))))))) -> Dependency open | L81: P05.03.02 | O81: =IF(AND(OR(L81="",IFNA(VLOOKUP(L81,$A$6:$H$80,8,FALSE),"Missing")="Verified"),OR(M81="",IFNA(VLOOKUP(M81,$A$6:$H$80,8,FALSE),"Missing")="Verified"),OR(N81="",IFNA(VLOOKUP(N81,$A$6:$H$80,8,FALSE),"Missing")="Verified")),"Ready","Dependency open") -> Dependency open | P81: Site consent, workload and food-service oversight recorded | Q81: Pilot protocol and permission | S81: 6000 | T81: J-K01 | U81: Proposed work; implementation not authorized by this documentation request. | V81: Expansion
A82: P05.03.04 | B82: P05 | C82: P05.03 Kitchen validation | D82: Choose continue revise or stop | E82: Evaluation reviewer | F82: Not started | G82: FALSE | H82: =IF(COUNTIFS($A$6:$A$161,A82)<>1,"Duplicate ID",IF(O82<>"Ready","Dependency open",IF(G82=TRUE,IF(AND(F82="Complete",I82<>"",J82<>"",K82<>""),"Verified","Evidence required"),IF(F82="Complete","Check completion",IF(F82="Blocked","Blocked",IF(F82="In progress","In progress",IF(F82="In review","In review","Open"))))))) -> Dependency open | L82: P05.03.03 | O82: =IF(AND(OR(L82="",IFNA(VLOOKUP(L82,$A$6:$H$81,8,FALSE),"Missing")="Verified"),OR(M82="",IFNA(VLOOKUP(M82,$A$6:$H$81,8,FALSE),"Missing")="Verified"),OR(N82="",IFNA(VLOOKUP(N82,$A$6:$H$81,8,FALSE),"Missing")="Verified")),"Ready","Dependency open") -> Dependency open | P82: Observed effort/correctness supports explicit decision | Q82: Kitchen gate report | S82: 6000 | T82: J-K01 | U82: Proposed work; implementation not authorized by this documentation request. | V82: Expansion
A83: P05.90.01 | B83: P05 | C83: P05.90 Phase gate | D83: Review and accept institutional kitchen extension | E83: Product owner + independent reviewer | F83: Not started | G83: FALSE | H83: =IF(COUNTIFS($A$6:$A$161,A83)<>1,"Duplicate ID",IF(O83<>"Ready","Dependency open",IF(G83=TRUE,IF(AND(F83="Complete",I83<>"",J83<>"",K83<>""),"Verified","Evidence required"),IF(F83="Complete","Check completion",IF(F83="Blocked","Blocked",IF(F83="In progress","In progress",IF(F83="In review","In review","Open"))))))) -> Dependency open | L83: P05.01.04 | M83: P05.02.04 | N83: P05.03.04 | O83: =IF(AND(OR(L83="",IFNA(VLOOKUP(L83,$A$6:$H$82,8,FALSE),"Missing")="Verified"),OR(M83="",IFNA(VLOOKUP(M83,$A$6:$H$82,8,FALSE),"Missing")="Verified"),OR(N83="",IFNA(VLOOKUP(N83,$A$6:$H$82,8,FALSE),"Missing")="Verified")),"Ready","Dependency open") -> Dependency open | P83: All prerequisites verified; critical risks closed or explicitly rejected for rollout; human records go/revise/stop decision. | Q83: Phase gate record with reviewer, evidence links, residual risks and next scope | S83: 4000 | T83: P05-GATE | U83: Unchecked until phase evidence is reviewed. A written plan is not implementation evidence. | V83: Expansion
A84: P06.01.01 | B84: P06 | C84: P06.01 Policy and donor eligibility | D84: Obtain qualified policy review | E84: Safety/partner lead | F84: Not started | G84: FALSE | H84: =IF(COUNTIFS($A$6:$A$161,A84)<>1,"Duplicate ID",IF(O84<>"Ready","Dependency open",IF(G84=TRUE,IF(AND(F84="Complete",I84<>"",J84<>"",K84<>""),"Verified","Evidence required"),IF(F84="Complete","Check completion",IF(F84="Blocked","Blocked",IF(F84="In progress","In progress",IF(F84="In review","In review","Open"))))))) -> Dependency open | L84: P04.90.01 | O84: =IF(AND(OR(L84="",IFNA(VLOOKUP(L84,$A$6:$H$83,8,FALSE),"Missing")="Verified"),OR(M84="",IFNA(VLOOKUP(M84,$A$6:$H$83,8,FALSE),"Missing")="Verified"),OR(N84="",IFNA(VLOOKUP(N84,$A$6:$H$83,8,FALSE),"Missing")="Verified")),"Ready","Dependency open") -> Dependency open | P84: Jurisdiction, category, source version and effective dates recorded | Q84: Policy sign-off | S84: 6000 | T84: J-R01 / REQ-POL-01 | U84: Proposed work; implementation not authorized by this documentation request. | V84: Expansion
A85: P06.01.02 | B85: P06 | C85: P06.01 Policy and donor eligibility | D85: Implement donor evidence completeness | E85: Safety/partner lead | F85: Not started | G85: FALSE | H85: =IF(COUNTIFS($A$6:$A$161,A85)<>1,"Duplicate ID",IF(O85<>"Ready","Dependency open",IF(G85=TRUE,IF(AND(F85="Complete",I85<>"",J85<>"",K85<>""),"Verified","Evidence required"),IF(F85="Complete","Check completion",IF(F85="Blocked","Blocked",IF(F85="In progress","In progress",IF(F85="In review","In review","Open"))))))) -> Dependency open | L85: P06.01.01 | O85: =IF(AND(OR(L85="",IFNA(VLOOKUP(L85,$A$6:$H$84,8,FALSE),"Missing")="Verified"),OR(M85="",IFNA(VLOOKUP(M85,$A$6:$H$84,8,FALSE),"Missing")="Verified"),OR(N85="",IFNA(VLOOKUP(N85,$A$6:$H$84,8,FALSE),"Missing")="Verified")),"Ready","Dependency open") -> Dependency open | P85: Unused/unserved status, custody and required handling records explicit | Q85: FoodOffer schema/evidence | S85: 6000 | T85: J-R01 / REQ-POL-01 | U85: Proposed work; implementation not authorized by this documentation request. | V85: Expansion
A86: P06.01.03 | B86: P06 | C86: P06.01 Policy and donor eligibility | D86: Block excluded or unreviewed offers | E86: Safety/partner lead | F86: Not started | G86: FALSE | H86: =IF(COUNTIFS($A$6:$A$161,A86)<>1,"Duplicate ID",IF(O86<>"Ready","Dependency open",IF(G86=TRUE,IF(AND(F86="Complete",I86<>"",J86<>"",K86<>""),"Verified","Evidence required"),IF(F86="Complete","Check completion",IF(F86="Blocked","Blocked",IF(F86="In progress","In progress",IF(F86="In review","In review","Open"))))))) -> Dependency open | L86: P06.01.02 | O86: =IF(AND(OR(L86="",IFNA(VLOOKUP(L86,$A$6:$H$85,8,FALSE),"Missing")="Verified"),OR(M86="",IFNA(VLOOKUP(M86,$A$6:$H$85,8,FALSE),"Missing")="Verified"),OR(N86="",IFNA(VLOOKUP(N86,$A$6:$H$85,8,FALSE),"Missing")="Verified")),"Ready","Dependency open") -> Dependency open | P86: Plate/spoiled food rejected; unknown state held for review | Q86: R negative cases | S86: 6000 | T86: J-R01 / REQ-POL-01 | U86: Proposed work; implementation not authorized by this documentation request. | V86: Expansion
A87: P06.01.04 | B87: P06 | C87: P06.01 Policy and donor eligibility | D87: Require human eligibility decision | E87: Safety/partner lead | F87: Not started | G87: FALSE | H87: =IF(COUNTIFS($A$6:$A$161,A87)<>1,"Duplicate ID",IF(O87<>"Ready","Dependency open",IF(G87=TRUE,IF(AND(F87="Complete",I87<>"",J87<>"",K87<>""),"Verified","Evidence required"),IF(F87="Complete","Check completion",IF(F87="Blocked","Blocked",IF(F87="In progress","In progress",IF(F87="In review","In review","Open"))))))) -> Dependency open | L87: P06.01.03 | O87: =IF(AND(OR(L87="",IFNA(VLOOKUP(L87,$A$6:$H$86,8,FALSE),"Missing")="Verified"),OR(M87="",IFNA(VLOOKUP(M87,$A$6:$H$86,8,FALSE),"Missing")="Verified"),OR(N87="",IFNA(VLOOKUP(N87,$A$6:$H$86,8,FALSE),"Missing")="Verified")),"Ready","Dependency open") -> Dependency open | P87: Reviewer identity and policy version persisted; AI cannot certify | Q87: Qualified review record | S87: 6000 | T87: J-R01 / REQ-POL-01 | U87: Proposed work; implementation not authorized by this documentation request. | V87: Expansion
A88: P06.02.01 | B88: P06 | C88: P06.02 Capacity and agreements | D88: Verify NGO and recipient organizations | E88: Partner operations lead | F88: Not started | G88: FALSE | H88: =IF(COUNTIFS($A$6:$A$161,A88)<>1,"Duplicate ID",IF(O88<>"Ready","Dependency open",IF(G88=TRUE,IF(AND(F88="Complete",I88<>"",J88<>"",K88<>""),"Verified","Evidence required"),IF(F88="Complete","Check completion",IF(F88="Blocked","Blocked",IF(F88="In progress","In progress",IF(F88="In review","In review","Open"))))))) -> Dependency open | L88: P04.90.01 | O88: =IF(AND(OR(L88="",IFNA(VLOOKUP(L88,$A$6:$H$87,8,FALSE),"Missing")="Verified"),OR(M88="",IFNA(VLOOKUP(M88,$A$6:$H$87,8,FALSE),"Missing")="Verified"),OR(N88="",IFNA(VLOOKUP(N88,$A$6:$H$87,8,FALSE),"Missing")="Verified")),"Ready","Dependency open") -> Dependency open | P88: Permissions, handling capability and contact consent documented | Q88: Partner onboarding evidence | S88: 6000 | T88: J-R01 / REQ-POL-01 | U88: Proposed work; implementation not authorized by this documentation request. | V88: Expansion
A89: P06.02.02 | B89: P06 | C89: P06.02 Capacity and agreements | D89: Record separate NGO and recipient acceptance | E89: Partner operations lead | F89: Not started | G89: FALSE | H89: =IF(COUNTIFS($A$6:$A$161,A89)<>1,"Duplicate ID",IF(O89<>"Ready","Dependency open",IF(G89=TRUE,IF(AND(F89="Complete",I89<>"",J89<>"",K89<>""),"Verified","Evidence required"),IF(F89="Complete","Check completion",IF(F89="Blocked","Blocked",IF(F89="In progress","In progress",IF(F89="In review","In review","Open"))))))) -> Dependency open | L89: P06.02.01 | O89: =IF(AND(OR(L89="",IFNA(VLOOKUP(L89,$A$6:$H$88,8,FALSE),"Missing")="Verified"),OR(M89="",IFNA(VLOOKUP(M89,$A$6:$H$88,8,FALSE),"Missing")="Verified"),OR(N89="",IFNA(VLOOKUP(N89,$A$6:$H$88,8,FALSE),"Missing")="Verified")),"Ready","Dependency open") -> Dependency open | P89: Capacity, diet, window and transport confirmed independently | Q89: Acceptance records | S89: 6000 | T89: J-R01 / REQ-POL-01 | U89: Proposed work; implementation not authorized by this documentation request. | V89: Expansion
A90: P06.02.03 | B90: P06 | C90: P06.02 Capacity and agreements | D90: Create scoped cross-tenant offer projection | E90: Partner operations lead | F90: Not started | G90: FALSE | H90: =IF(COUNTIFS($A$6:$A$161,A90)<>1,"Duplicate ID",IF(O90<>"Ready","Dependency open",IF(G90=TRUE,IF(AND(F90="Complete",I90<>"",J90<>"",K90<>""),"Verified","Evidence required"),IF(F90="Complete","Check completion",IF(F90="Blocked","Blocked",IF(F90="In progress","In progress",IF(F90="In review","In review","Open"))))))) -> Dependency open | L90: P06.02.02 | O90: =IF(AND(OR(L90="",IFNA(VLOOKUP(L90,$A$6:$H$89,8,FALSE),"Missing")="Verified"),OR(M90="",IFNA(VLOOKUP(M90,$A$6:$H$89,8,FALSE),"Missing")="Verified"),OR(N90="",IFNA(VLOOKUP(N90,$A$6:$H$89,8,FALSE),"Missing")="Verified")),"Ready","Dependency open") -> Dependency open | P90: Only approved fields shared; no donor inventory disclosure | Q90: Sharing security review | S90: 6000 | T90: J-R01 / REQ-POL-01 | U90: Proposed work; implementation not authorized by this documentation request. | V90: Expansion
A91: P06.02.04 | B91: P06 | C91: P06.02 Capacity and agreements | D91: Reserve capacity and revalidate at approval | E91: Partner operations lead | F91: Not started | G91: FALSE | H91: =IF(COUNTIFS($A$6:$A$161,A91)<>1,"Duplicate ID",IF(O91<>"Ready","Dependency open",IF(G91=TRUE,IF(AND(F91="Complete",I91<>"",J91<>"",K91<>""),"Verified","Evidence required"),IF(F91="Complete","Check completion",IF(F91="Blocked","Blocked",IF(F91="In progress","In progress",IF(F91="In review","In review","Open"))))))) -> Dependency open | L91: P06.02.03 | O91: =IF(AND(OR(L91="",IFNA(VLOOKUP(L91,$A$6:$H$90,8,FALSE),"Missing")="Verified"),OR(M91="",IFNA(VLOOKUP(M91,$A$6:$H$90,8,FALSE),"Missing")="Verified"),OR(N91="",IFNA(VLOOKUP(N91,$A$6:$H$90,8,FALSE),"Missing")="Verified")),"Ready","Dependency open") -> Dependency open | P91: Expiry, cancellation and concurrent claims prevent double dispatch | Q91: Reservation race evidence | S91: 6000 | T91: J-R01 / REQ-POL-01 | U91: Proposed work; implementation not authorized by this documentation request. | V91: Expansion
A92: P06.03.01 | B92: P06 | C92: P06.03 Custody and exception handling | D92: Record pickup delivery and accepted mass | E92: Partner operations lead | F92: Not started | G92: FALSE | H92: =IF(COUNTIFS($A$6:$A$161,A92)<>1,"Duplicate ID",IF(O92<>"Ready","Dependency open",IF(G92=TRUE,IF(AND(F92="Complete",I92<>"",J92<>"",K92<>""),"Verified","Evidence required"),IF(F92="Complete","Check completion",IF(F92="Blocked","Blocked",IF(F92="In progress","In progress",IF(F92="In review","In review","Open"))))))) -> Dependency open | L92: P04.90.01 | O92: =IF(AND(OR(L92="",IFNA(VLOOKUP(L92,$A$6:$H$91,8,FALSE),"Missing")="Verified"),OR(M92="",IFNA(VLOOKUP(M92,$A$6:$H$91,8,FALSE),"Missing")="Verified"),OR(N92="",IFNA(VLOOKUP(N92,$A$6:$H$91,8,FALSE),"Missing")="Verified")),"Ready","Dependency open") -> Dependency open | P92: Signed actor/time/evidence at each custody change | Q92: Custody ledger | S92: 6000 | T92: J-R01 / REQ-POL-01 | U92: Proposed work; implementation not authorized by this documentation request. | V92: Expansion
A93: P06.03.02 | B93: P06 | C93: P06.03 Custody and exception handling | D93: Handle partial rejection and failed delivery | E93: Partner operations lead | F93: Not started | G93: FALSE | H93: =IF(COUNTIFS($A$6:$A$161,A93)<>1,"Duplicate ID",IF(O93<>"Ready","Dependency open",IF(G93=TRUE,IF(AND(F93="Complete",I93<>"",J93<>"",K93<>""),"Verified","Evidence required"),IF(F93="Complete","Check completion",IF(F93="Blocked","Blocked",IF(F93="In progress","In progress",IF(F93="In review","In review","Open"))))))) -> Dependency open | L93: P06.03.01 | O93: =IF(AND(OR(L93="",IFNA(VLOOKUP(L93,$A$6:$H$92,8,FALSE),"Missing")="Verified"),OR(M93="",IFNA(VLOOKUP(M93,$A$6:$H$92,8,FALSE),"Missing")="Verified"),OR(N93="",IFNA(VLOOKUP(N93,$A$6:$H$92,8,FALSE),"Missing")="Verified")),"Ready","Dependency open") -> Dependency open | P93: No automatic reroute; accountable human chooses permitted disposition | Q93: Exception walkthrough | S93: 6000 | T93: J-R01 / REQ-POL-01 | U93: Proposed work; implementation not authorized by this documentation request. | V93: Expansion
A94: P06.03.03 | B94: P06 | C94: P06.03 Custody and exception handling | D94: Implement withdrawal and incident escalation | E94: Partner operations lead | F94: Not started | G94: FALSE | H94: =IF(COUNTIFS($A$6:$A$161,A94)<>1,"Duplicate ID",IF(O94<>"Ready","Dependency open",IF(G94=TRUE,IF(AND(F94="Complete",I94<>"",J94<>"",K94<>""),"Verified","Evidence required"),IF(F94="Complete","Check completion",IF(F94="Blocked","Blocked",IF(F94="In progress","In progress",IF(F94="In review","In review","Open"))))))) -> Dependency open | L94: P06.03.02 | O94: =IF(AND(OR(L94="",IFNA(VLOOKUP(L94,$A$6:$H$93,8,FALSE),"Missing")="Verified"),OR(M94="",IFNA(VLOOKUP(M94,$A$6:$H$93,8,FALSE),"Missing")="Verified"),OR(N94="",IFNA(VLOOKUP(N94,$A$6:$H$93,8,FALSE),"Missing")="Verified")),"Ready","Dependency open") -> Dependency open | P94: Revoked offers cannot dispatch; incidents linked to affected batches | Q94: Recall/escalation evidence | S94: 6000 | T94: J-R01 / REQ-POL-01 | U94: Proposed work; implementation not authorized by this documentation request. | V94: Expansion
A95: P06.03.04 | B95: P06 | C95: P06.03 Custody and exception handling | D95: Run simulation before any live pilot | E95: Partner operations lead | F95: Not started | G95: FALSE | H95: =IF(COUNTIFS($A$6:$A$161,A95)<>1,"Duplicate ID",IF(O95<>"Ready","Dependency open",IF(G95=TRUE,IF(AND(F95="Complete",I95<>"",J95<>"",K95<>""),"Verified","Evidence required"),IF(F95="Complete","Check completion",IF(F95="Blocked","Blocked",IF(F95="In progress","In progress",IF(F95="In review","In review","Open"))))))) -> Dependency open | L95: P06.03.03 | O95: =IF(AND(OR(L95="",IFNA(VLOOKUP(L95,$A$6:$H$94,8,FALSE),"Missing")="Verified"),OR(M95="",IFNA(VLOOKUP(M95,$A$6:$H$94,8,FALSE),"Missing")="Verified"),OR(N95="",IFNA(VLOOKUP(N95,$A$6:$H$94,8,FALSE),"Missing")="Verified")),"Ready","Dependency open") -> Dependency open | P95: R-lane red-team cases pass and physical partner authorization explicit | Q95: Recovery pilot readiness report | S95: 6000 | T95: J-R01 / REQ-POL-01 | U95: Proposed work; implementation not authorized by this documentation request. | V95: Expansion
A96: P06.90.01 | B96: P06 | C96: P06.90 Phase gate | D96: Review and accept qualified recovery coordination | E96: Product owner + independent reviewer | F96: Not started | G96: FALSE | H96: =IF(COUNTIFS($A$6:$A$161,A96)<>1,"Duplicate ID",IF(O96<>"Ready","Dependency open",IF(G96=TRUE,IF(AND(F96="Complete",I96<>"",J96<>"",K96<>""),"Verified","Evidence required"),IF(F96="Complete","Check completion",IF(F96="Blocked","Blocked",IF(F96="In progress","In progress",IF(F96="In review","In review","Open"))))))) -> Dependency open | L96: P06.01.04 | M96: P06.02.04 | N96: P06.03.04 | O96: =IF(AND(OR(L96="",IFNA(VLOOKUP(L96,$A$6:$H$95,8,FALSE),"Missing")="Verified"),OR(M96="",IFNA(VLOOKUP(M96,$A$6:$H$95,8,FALSE),"Missing")="Verified"),OR(N96="",IFNA(VLOOKUP(N96,$A$6:$H$95,8,FALSE),"Missing")="Verified")),"Ready","Dependency open") -> Dependency open | P96: All prerequisites verified; critical risks closed or explicitly rejected for rollout; human records go/revise/stop decision. | Q96: Phase gate record with reviewer, evidence links, residual risks and next scope | S96: 4000 | T96: P06-GATE | U96: Unchecked until phase evidence is reviewed. A written plan is not implementation evidence. | V96: Expansion
A97: P07.01.01 | B97: P07 | C97: P07.01 Accepted loads | D97: Verify local operator and accepted-material rules | E97: Processor partner lead | F97: Not started | G97: FALSE | H97: =IF(COUNTIFS($A$6:$A$161,A97)<>1,"Duplicate ID",IF(O97<>"Ready","Dependency open",IF(G97=TRUE,IF(AND(F97="Complete",I97<>"",J97<>"",K97<>""),"Verified","Evidence required"),IF(F97="Complete","Check completion",IF(F97="Blocked","Blocked",IF(F97="In progress","In progress",IF(F97="In review","In review","Open"))))))) -> Dependency open | L97: P06.90.01 | O97: =IF(AND(OR(L97="",IFNA(VLOOKUP(L97,$A$6:$H$96,8,FALSE),"Missing")="Verified"),OR(M97="",IFNA(VLOOKUP(M97,$A$6:$H$96,8,FALSE),"Missing")="Verified"),OR(N97="",IFNA(VLOOKUP(N97,$A$6:$H$96,8,FALSE),"Missing")="Verified")),"Ready","Dependency open") -> Dependency open | P97: Operator authorization and exclusions documented per site | Q97: Operator/policy record | S97: 6000 | T97: J-O01 / REQ-IMPACT-01 | U97: Proposed work; implementation not authorized by this documentation request. | V97: Expansion
A98: P07.01.02 | B98: P07 | C98: P07.01 Accepted loads | D98: Capture segregated source load | E98: Processor partner lead | F98: Not started | G98: FALSE | H98: =IF(COUNTIFS($A$6:$A$161,A98)<>1,"Duplicate ID",IF(O98<>"Ready","Dependency open",IF(G98=TRUE,IF(AND(F98="Complete",I98<>"",J98<>"",K98<>""),"Verified","Evidence required"),IF(F98="Complete","Check completion",IF(F98="Blocked","Blocked",IF(F98="In progress","In progress",IF(F98="In review","In review","Open"))))))) -> Dependency open | L98: P07.01.01 | O98: =IF(AND(OR(L98="",IFNA(VLOOKUP(L98,$A$6:$H$97,8,FALSE),"Missing")="Verified"),OR(M98="",IFNA(VLOOKUP(M98,$A$6:$H$97,8,FALSE),"Missing")="Verified"),OR(N98="",IFNA(VLOOKUP(N98,$A$6:$H$97,8,FALSE),"Missing")="Verified")),"Ready","Dependency open") -> Dependency open | P98: Origin, category, quantity and contaminated fraction explicit | Q98: J-O01 load record | S98: 6000 | T98: J-O01 / REQ-IMPACT-01 | U98: Proposed work; implementation not authorized by this documentation request. | V98: Expansion
A99: P07.01.03 | B99: P07 | C99: P07.01 Accepted loads | D99: Record calibrated gross tare and net weights | E99: Processor partner lead | F99: Not started | G99: FALSE | H99: =IF(COUNTIFS($A$6:$A$161,A99)<>1,"Duplicate ID",IF(O99<>"Ready","Dependency open",IF(G99=TRUE,IF(AND(F99="Complete",I99<>"",J99<>"",K99<>""),"Verified","Evidence required"),IF(F99="Complete","Check completion",IF(F99="Blocked","Blocked",IF(F99="In progress","In progress",IF(F99="In review","In review","Open"))))))) -> Dependency open | L99: P07.01.02 | O99: =IF(AND(OR(L99="",IFNA(VLOOKUP(L99,$A$6:$H$98,8,FALSE),"Missing")="Verified"),OR(M99="",IFNA(VLOOKUP(M99,$A$6:$H$98,8,FALSE),"Missing")="Verified"),OR(N99="",IFNA(VLOOKUP(N99,$A$6:$H$98,8,FALSE),"Missing")="Verified")),"Ready","Dependency open") -> Dependency open | P99: Units, scale, timestamp and operator attestation preserved | Q99: Weigh ticket | S99: 6000 | T99: J-O01 / REQ-IMPACT-01 | U99: Proposed work; implementation not authorized by this documentation request. | V99: Expansion
A100: P07.01.04 | B100: P07 | C100: P07.01 Accepted loads | D100: Reject contaminated or unauthorized collection | E100: Processor partner lead | F100: Not started | G100: FALSE | H100: =IF(COUNTIFS($A$6:$A$161,A100)<>1,"Duplicate ID",IF(O100<>"Ready","Dependency open",IF(G100=TRUE,IF(AND(F100="Complete",I100<>"",J100<>"",K100<>""),"Verified","Evidence required"),IF(F100="Complete","Check completion",IF(F100="Blocked","Blocked",IF(F100="In progress","In progress",IF(F100="In review","In review","Open"))))))) -> Dependency open | L100: P07.01.03 | O100: =IF(AND(OR(L100="",IFNA(VLOOKUP(L100,$A$6:$H$99,8,FALSE),"Missing")="Verified"),OR(M100="",IFNA(VLOOKUP(M100,$A$6:$H$99,8,FALSE),"Missing")="Verified"),OR(N100="",IFNA(VLOOKUP(N100,$A$6:$H$99,8,FALSE),"Missing")="Verified")),"Ready","Dependency open") -> Dependency open | P100: No assumed composting route for every organic material | Q100: Load rejection evidence | S100: 6000 | T100: J-O01 / REQ-IMPACT-01 | U100: Proposed work; implementation not authorized by this documentation request. | V100: Expansion
A101: P07.02.01 | B101: P07 | C101: P07.02 Processing chain | D101: Record collected accepted rejected and processed stages | E101: Backend/operations team | F101: Not started | G101: FALSE | H101: =IF(COUNTIFS($A$6:$A$161,A101)<>1,"Duplicate ID",IF(O101<>"Ready","Dependency open",IF(G101=TRUE,IF(AND(F101="Complete",I101<>"",J101<>"",K101<>""),"Verified","Evidence required"),IF(F101="Complete","Check completion",IF(F101="Blocked","Blocked",IF(F101="In progress","In progress",IF(F101="In review","In review","Open"))))))) -> Dependency open | L101: P06.90.01 | O101: =IF(AND(OR(L101="",IFNA(VLOOKUP(L101,$A$6:$H$100,8,FALSE),"Missing")="Verified"),OR(M101="",IFNA(VLOOKUP(M101,$A$6:$H$100,8,FALSE),"Missing")="Verified"),OR(N101="",IFNA(VLOOKUP(N101,$A$6:$H$100,8,FALSE),"Missing")="Verified")),"Ready","Dependency open") -> Dependency open | P101: Each stage separate; pickup never treated as processing | Q101: Stage ledger | S101: 6000 | T101: J-O01 / REQ-IMPACT-01 | U101: Proposed work; implementation not authorized by this documentation request. | V101: Expansion
...

Sheet Decisions
A1: Decisions and tradeoffs
A2: Proposed / recommended is not human approval. Record evidence, approver and date when resolved.
A5: Decision ID | B5: Choice | C5: Disposition | D5: Recommendation | E5: Alternatives | F5: Reason | G5: Owner role | H5: Linked unit | I5: Revisit trigger | J5: Evidence | K5: Approver | L5: Decision date
A6: DEC-PLAT-001 | B6: First implementation lane | C6: Proposed | D6: One household changed-plan journey; switch to kitchen first only with better actor/data access | E6: Three full lanes at once; generic material marketplace | F6: Small enough to prove the shared loop; competition and residual gap still unknown | G6: Product owner | H6: P00.01.03 | I6: Observed actor access and residual pain change the preferred lane
A7: DEC-PLAT-002 | B7: Platform expansion | C7: Proposed | D7: Shared trust/evidence/action core with separately gated domain modules | E7: One universal resource engine; separate disconnected apps | F7: Reuse coordination contracts without conflating food safety, repair and meter authority | G7: Product owner + technical lead | H7: P08.90.01 | I7: Second domain cannot reuse core safely or does not show demand
A8: DEC-PLAT-003 | B8: Backend structure | C8: Recommended | D8: Modular FastAPI monolith and bounded worker when required | E8: Microservices from day one; frontend-only logic | F8: Fewer transaction and deployment seams while preserving domain boundaries | G8: Technical lead | H8: P01.90.01 | I8: Measured scaling, security ownership or release independence justifies split
A9: DEC-PLAT-004 | B9: Runtime compatibility | C9: Open | D9: Verify current Next.js/Node support on App Hosting before pinning deployment pair | E9: Assume repo version works; automatically downgrade | F9: Existing package version and retrieved support schedule differ; no deploy proof | G9: Platform lead | H9: P01.03.01 | I9: Official support or a measured deployed compatibility test settles pair
A10: DEC-PLAT-005 | B10: Canonical storage | C10: Existing stack constraint | D10: Firestore versioned document state and Cloud Storage media; reevaluate relational needs later | E10: PostgreSQL now; in-memory canonical state | F10: Fits selected stack and bounded workflows; cross-org joins need careful projections | G10: Technical lead | H10: P01.02.04 | I10: Transaction contention or reporting constraints dominate
A11: DEC-PLAT-006 | B11: Authorization | C11: Required invariant | D11: Verified identity plus active membership, role, consent and resource scope; fail closed | E11: Trust body tenant ID; default tenant; token-only organization membership | F11: Prevent cross-tenant reads and stale authority after revocation | G11: Security/backend lead | H11: P01.01.04 | I11: No relaxation; improve implementation with equivalent or stronger proof
A12: DEC-PLAT-007 | B12: Facts and approvals | C12: Required invariant | D12: Candidate isolation; explicit confirmation; immutable version-bound preview and authorized approval | E12: Agent writes facts or self-authorizes execution | F12: Human authority and current source state govern every physical effect | G12: Technical lead | H12: P03.02.04 | I12: No relaxation; contract changes require migration and denial checks
A13: DEC-PLAT-008 | B13: Food policy | C13: Required invariant | D13: Reviewed category/site policy bundles; missing applicability holds for review | E13: Universal hardcoded time/temperature thresholds from examples | F13: Current local shortcuts are not established by cited rule text | G13: Qualified policy owner | H13: P06.01.01 | I13: Reviewed official amendment or site policy updates versioned bundle
A14: DEC-PLAT-009 | B14: AI structure | C14: Recommended | D14: Structured extraction and one bounded allowlisted ADK coordinator, evaluated separately | E14: Multi-agent product runtime; unlimited tool loop; rules-only forever | F14: AI may help ambiguity; arithmetic and authority stay deterministic | G14: AI lead | H14: P03.03.04 | I14: Comparison shows a step adds no benefit or a justified workflow needs more
A15: DEC-PLAT-010 | B15: Policy retrieval | C15: Deferred | D15: Small reviewed rule table and source links first | E15: Vertex AI Search/RAG immediately | F15: Corpus size and retrieval need are unproven; retrieved prose cannot publish policy | G15: Policy/AI lead | H15: P06.01.01 | I15: Authorized corpus and real questions show retrieval improves the task
A16: DEC-PLAT-011 | B16: Jobs and external actions | C16: Recommended | D16: Outbox plus idempotent worker for durable effects; reconcile ambiguous provider states | E16: Provider call inside transaction; blind retry after timeout | F16: Transactions can retry and networks duplicate or hide successful effects | G16: Backend lead | H16: P03.02.04 | I16: A synchronous bounded demo needs no durable external work; keep effect boundary
A17: DEC-PLAT-012 | B17: Product real-time behavior | C17: Recommended | D17: Bounded polling with versions initially; scoped events only after measured need | E17: Persistent streams everywhere; unscoped global listeners | F17: Recoverable and easier to secure; acknowledgement and timestamps matter first | G17: Fullstack lead | H17: P03.03.03 | I17: Collaboration latency/read costs justify streams
... A25: DEC-PLAT-020 | B25: Current work authorization | C25: User constraint | D25: Documentation/research and live planning artifacts only; implementation requires later direction | E25: Treat this request as permission to modify application code or deploy | F25: User explicitly requested ideation, tradeoffs and feasibility with no code changes | G25: Product owner | H25: P00.03.04 | I25: User explicitly authorizes implementation scope

Sheet Risks
A1: Risks and next evidence
A5: Risk ID | B5: Risk | C5: State | D5: Trigger | E5: Response / next evidence | F5: Owner role | G5: Linked unit | H5: Evidence / update | I5: Disposition
A6: RISK-01 | B6: Residual pain unproven | C6: Open | D6: Existing list/service handles chosen cases | E6: Reconstruct real episodes and compare baseline | F6: Product owner | G6: P00.01.02 | I6: Unresolved
A7: RISK-02 | B7: Data rights or authority unavailable | C7: Open | D7: No consenting source/decision owner | E7: Obtain artifact rights or defer feature | F7: Research lead | G7: P00.02.04 | I7: Unresolved
A8: RISK-03 | B8: Unsafe policy shortcut | C8: Open | D8: Unreviewed threshold or food-safety claim | E8: Block live recovery; qualified policy review | F8: Policy owner | G8: P06.01.01 | I8: Unresolved
A9: RISK-04 | B9: Deployment or model access blocked | C9: Open | D9: Unsupported runtime/IAM/quota | E9: Verify early and cut optional scope | F9: Platform lead | G9: P01.03.01 | I9: Unresolved
A10: RISK-05 | B10: Input burden exceeds benefit | C10: Open | D10: Corrections take longer than baseline | E10: Measure all actor effort; redesign capture | F10: Product lead | G10: P08.01.03 | I10: Unresolved
A11: RISK-06 | B11: AI adds no incremental value | C11: Open | D11: No better correctness/effort net of cost | E11: Keep rules; remove unnecessary model step | F11: AI/evaluation lead | G11: P03.03.04 | I11: Unresolved
A12: RISK-07 | B12: Physical logistics dominates | C12: Open | D12: No safe capacity or processing destination | E12: Audit failures; a directory cannot create capacity | F12: Partner lead | G12: P06.02.02 | I12: Unresolved
A13: RISK-08 | B13: Impact overclaim/double counting | C13: Open | D13: Simulation shown as measured saving | E13: Separate stage, origin, verification and attribution | F13: Measurement lead | G13: P08.03.04 | I13: Unresolved
A14: RISK-09 | B14: Economics or payer unproven | C14: Open | D14: Support exceeds payer value | E14: Measure costs and real pricing response | F14: Product owner | G14: P08.02.04 | I14: Unresolved
A15: RISK-10 | B15: Context drift/false completion | C15: Open | D15: Missing evidence or duplicate live status | E15: Stable IDs, gates and session handoff | F15: Technical lead | G15: P00.03.03 | I15: Unresolved

Sheet Sessions
A1: Session handoffs
A5: Session ID | B5: Date (IST) | C5: Scope | D5: Units / artifacts | E5: Evidence | F5: Result | G5: Open blocker | H5: Next unit | I5: Decisions | J5: Usage note
A6: S-2026-10-15-01 | B6: 2026-10-15 | C6: Research and documentation only | D6: 42 sources; blueprint + 156-unit plan | E6: Control room/source register | F6: Documentation prepared; implementation unverified | G6: Human review, access and scope decisions pending | H6: P00.01.01 | I6: DEC-PLAT-001–020 as labeled | J6: Actual account budget unknown; bounded task packets

Sheet Guide
A1: How to keep this harness current
A5: Topic | B5: Operating rule
A6: Authority | B6: Tasks is live status; Docs are narrative; local files are snapshots.
A7: Completion | B7: Set Complete + Done + evidence + reviewer + updated date. Dependencies must be Verified.
A8: Formula limit | B8: Use filters, not physical sorting. Dependencies must point to earlier unique IDs; missing/later IDs fail closed.
A9: Adding work | B9: Append unique IDs after prerequisites, copy formulas/validation, extend bounded ranges and update phase gates.
A10: No background sync | B10: No repository monitor, CI integration, agent scheduler or two-way Drive sync is implemented.
A11: Ownership | B11: Initial owners are roles. Assign actual people/agents before execution.
A12: Token allowance | B12: 6,000 context tokens/unit is a planning input; actual output/tool/delegation usage varies.
A13: Evidence quality | B13: Formulas check presence/state, not truth, safety qualification or link accessibility.
A14: Scope | B14: Documentation only. Later code, deployment and physical effects require relevant direction.
A15: Review | B15: Critical auth/safety/data-loss review first, then maintainability, UX and missing checks.
A16: Recovery | B16: Back up before structural changes; preserve IDs, revisions, failed output and decisions.
A17: Source folder | B17: https://drive.google.com/drive/folders/1iTwjBm5FrwthFEzuTZ91D33sRSB4ft9v
